Workbook

Sheet Dashboard
A1: Virgo Operations Hub — MRP Dashboard
A2: Real-time overview across all modules
A4: Metric | B4: Value | C4: Formula Source | D4: Status
A5: Open Sales Orders | B5: =COUNTIF('Sales Orders'!K4:K100,"Open") -> 20 | C5: Sales Orders!K | D5: =IF(B5="","—",IF(OR(AND(A5="Low Stock Alerts",B5>5),AND(A5="Open Sales Orders",B5>20)),"⚠ Review","✓ OK")) -> ✓ OK
A6: Total SO Revenue (pending) | B6: =SUMPRODUCT(('Sales Orders'!K4:K100="Open")*('Sales Orders'!I4:I100)) -> 19740.09 | C6: Sales Orders!I | D6: =IF(B6="","—",IF(OR(AND(A6="Low Stock Alerts",B6>5),AND(A6="Open Sales Orders",B6>20)),"⚠ Review","✓ OK")) -> ✓ OK
A7: Total SKUs in Inventory | B7: =COUNTA(Inventory!A4:A500) -> 6 | C7: Inventory!A | D7: =IF(B7="","—",IF(OR(AND(A7="Low Stock Alerts",B7>5),AND(A7="Open Sales Orders",B7>20)),"⚠ Review","✓ OK")) -> ✓ OK
A8: Low Stock Alerts | B8: =COUNTIF(Inventory!J4:J500,"LOW") -> 1 | C8: Inventory!J | D8: =IF(B8="","—",IF(OR(AND(A8="Low Stock Alerts",B8>5),AND(A8="Open Sales Orders",B8>20)),"⚠ Review","✓ OK")) -> ✓ OK
A9: Open Make Orders | B9: =COUNTIF('Make Orders'!J4:J100,"In Progress")+COUNTIF('Make Orders'!J4:J100,"Planned") -> 3 | C9: Make Orders!J | D9: =IF(B9="","—",IF(OR(AND(A9="Low Stock Alerts",B9>5),AND(A9="Open Sales Orders",B9>20)),"⚠ Review","✓ OK")) -> ✓ OK
A10: Open Purchase Orders | B10: =COUNTIF('Vendors & POs'!L4:L100,"Open")+COUNTIF('Vendors & POs'!L4:L100,"Partial") -> 3 | C10: Vendors & POs!L | D10: =IF(B10="","—",IF(OR(AND(A10="Low Stock Alerts",B10>5),AND(A10="Open Sales Orders",B10>20)),"⚠ Review","✓ OK")) -> ✓ OK
A11: Shipments In Transit | B11: =COUNTIF('Shipping & Tracking'!J4:J100,"In Transit") -> 3 | C11: Shipping!J | D11: =IF(B11="","—",IF(OR(AND(A11="Low Stock Alerts",B11>5),AND(A11="Open Sales Orders",B11>20)),"⚠ Review","✓ OK")) -> ✓ OK
A12: Active BOMs | B12: =COUNTA(BOMs!A4:A500) -> 12 | C12: BOMs!A | D12: =IF(B12="","—",IF(OR(AND(A12="Low Stock Alerts",B12>5),AND(A12="Open Sales Orders",B12>20)),"⚠ Review","✓ OK")) -> ✓ OK
A13: Total Customers | B13: =COUNTA(Customers!A4:A500) -> 50 | C13: Customers!A | D13: =IF(B13="","—",IF(OR(AND(A13="Low Stock Alerts",B13>5),AND(A13="Open Sales Orders",B13>20)),"⚠ Review","✓ OK")) -> ✓ OK
A14: Total Products | B14: =COUNTA(Products!A4:A500) -> 5 | C14: Products!A | D14: =IF(B14="","—",IF(OR(AND(A14="Low Stock Alerts",B14>5),AND(A14="Open Sales Orders",B14>20)),"⚠ Review","✓ OK")) -> ✓ OK
A15: Inventory Value | B15: =SUMPRODUCT(Inventory!E4:E100,Inventory!K4:K100) -> 42645 | C15: Inventory!E x K | D15: =IF(B15="","—",IF(OR(AND(A15="Low Stock Alert Count",B15>3),AND(A15="Overdue Purchase Orders",B15>0)),"⚠ Review","✓ OK")) -> ✓ OK
A16: Revenue (30 days) | B16: =SUMPRODUCT((DATEVALUE('Sales Orders'!B4:B53)>=TODAY()-30)*('Sales Orders'!K4:K53="Delivered")*('Sales Orders'!I4:I53)) -> 174.99 | C16: SO date+status+amount | D16: =IF(B16="","—",IF(OR(AND(A16="Low Stock Alert Count",B16>3),AND(A16="Overdue Purchase Orders",B16>0)),"⚠ Review","✓ OK")) -> ✓ OK
A17: Fulfilled (30 days) | B17: =SUMPRODUCT((DATEVALUE('Sales Orders'!B4:B53)>=TODAY()-30)*('Sales Orders'!M4:M53="Fulfilled")*1) -> 5 | C17: SO date+fulfillment | D17: =IF(B17="","—",IF(OR(AND(A17="Low Stock Alert Count",B17>3),AND(A17="Overdue Purchase Orders",B17>0)),"⚠ Review","✓ OK")) -> ✓ OK
A18: Avg Order Value | B18: =IFERROR(AVERAGE('Sales Orders'!I4:I100),"—") -> 813.1832 | C18: Sales Orders!I | D18: =IF(B18="","—",IF(OR(AND(A18="Low Stock Alert Count",B18>3),AND(A18="Overdue Purchase Orders",B18>0)),"⚠ Review","✓ OK")) -> ✓ OK
A19: Low Stock Alert Count | B19: =COUNTIF(Inventory!U4:U100,"REORDER")+COUNTIF(Inventory!U4:U100,"ORDER NOW") -> 1 | C19: Inventory!U | D19: =IF(B19="","—",IF(OR(AND(A19="Low Stock Alert Count",B19>3),AND(A19="Overdue Purchase Orders",B19>0)),"⚠ Review","✓ OK")) -> ✓ OK
A20: Overdue Purchase Orders | B20: =COUNTIF('Vendors & POs'!W4:W100,">"&0) -> 0 | C20: Vendors & POs!W | D20: =IF(B20="","—",IF(OR(AND(A20="Low Stock Alert Count",B20>3),AND(A20="Overdue Purchase Orders",B20>0)),"⚠ Review","✓ OK")) -> ✓ OK
A21: Predicted Days to Stockout | B21: =IFERROR(MIN(Inventory!T4:T100),"N/A") -> 39 | C21: Inventory!T | D21: =IF(B21="","—",IF(OR(AND(A21="Low Stock Alert Count",B21>3),AND(A21="Overdue Purchase Orders",B21>0)),"⚠ Review","✓ OK")) -> ✓ OK
A22: Active Serials Shipped | B22: =COUNTIF('Serial Tracker'!L14:L463,"<>In Stock") -> 39 | C22: Serial Tracker!L | D22: =IF(B22="","—",IF(OR(AND(A22="Low Stock Alert Count",B22>3),AND(A22="Overdue Purchase Orders",B22>0)),"⚠ Review","✓ OK")) -> ✓ OK
A23: Open HubSpot Tickets | B23: =COUNTIF('Serial Tracker'!N14:N463,"HS-*") -> 9 | C23: Serial Tracker!N | D23: =IF(B23="","—",IF(OR(AND(A23="Low Stock Alert Count",B23>3),AND(A23="Overdue Purchase Orders",B23>0)),"⚠ Review","✓ OK")) -> ✓ OK
A24: Units Pending Shipment | B24: =COUNTIF('Shipping & Tracking'!J4:J100,"Pending") -> 33 | C24: Shipping!J | D24: =IF(B24="","—",IF(OR(AND(A24="Low Stock Alert Count",B24>3),AND(A24="Overdue Purchase Orders",B24>0)),"⚠ Review","✓ OK")) -> ✓ OK
A25: Customers | B25: Customer database | C25: Contact info, Shopify/HubSpot IDs, order history summary
A27: Demand Forecast & Planning
A28: Metric | B28: Value | C28: Formula | D28: Notes
A29: Orders (Last 30 Days) | B29: =SUMPRODUCT((DATEVALUE('Sales Orders'!B4:B53)>=TODAY()-30)*1) -> 22 | C29: COUNTIFS on date | D29: Rolling window
A30: Orders (Last 60 Days) | B30: =SUMPRODUCT((DATEVALUE('Sales Orders'!B4:B53)>=TODAY()-60)*1) -> 49 | C30: COUNTIFS on date | D30: Rolling window
A31: Orders (Last 90 Days) | B31: =SUMPRODUCT((DATEVALUE('Sales Orders'!B4:B53)>=TODAY()-90)*1) -> 50 | C31: COUNTIFS on date | D31: Rolling window
A32: Avg Daily Order Rate (30d) | B32: =IFERROR(B29/30,0) -> 0.73333333 | C32: Orders / 30 | D32: Key demand signal
A33: Projected Monthly Demand | B33: =ROUND(B32*30,0) -> 22 | C33: Daily rate x 30 | D33: Next 30-day projection
A34: Months of Inventory Remaining | B34: =IFERROR(ROUND(SUM(Inventory!E4:E100)/MAX(B33,1),1),"N/A") -> 30.2 | C34: Total stock / monthly demand | D34: Runway estimate
A35: Revenue Velocity ($/day, 30d) | B35: =IFERROR(SUMPRODUCT((DATEVALUE('Sales Orders'!B4:B53)>=TODAY()-30)*('Sales Orders'!I4:I53))/30,0) -> 549.29267 | C35: Revenue / 30 days | D35: Revenue burn rate
A38: Module Quick Reference
A39: Module | B39: Integration | C39: Description
A40: Sales Orders | B40: Shopify + HubSpot sync | C40: Orders, fulfillment status, returns/RMA tracking
A41: Inventory | B41: Real-time stock + alerts | C41: On-hand, reserved, available; reorder alerts; days-on-hand
A42: Make Orders | B42: Manufacturing/production | C42: Production runs, material consumption, labor, WIP
A43: Vendors & POs | B43: Supplier management | C43: POs, lead times, costs, receipt variance, overdue tracking
A44: BOMs | B44: Bill of Materials | C44: Multi-level BOMs, parent assemblies, waste-adjusted qty, cost rollups
A45: Serial Tracker | B45: Traceability (NEW) | C45: 450 serials × 5 batches → customer, warranty, HubSpot tickets
A46: Shipping & Tracking | B46: Freightcom integration | C46: 76 real shipments, tracking, carriers, delivery confirmation
A47: Products | B47: Master catalog | C47: SKU, pricing, reorder points, lead times, min order qty
A48: Customers | B48: Customer database | C48: 50 contacts, Shopify/HubSpot IDs, order history

Sheet Sales Orders
A1: Sales Orders
A2: Synced from Shopify & HubSpot — Track fulfillment end-to-end
A3: SO Number | B3: Order Date | C3: Channel | D3: Channel Order ID | E3: Customer Name | F3: Customer Email | G3: Products (SKUs) | H3: Qty | I3: Total Amount | J3: Currency | K3: Status | L3: Payment Status | M3: Fulfillment Status | N3: Assigned Warehouse | O3: Make Order Ref | P3: Ship By Date | Q3: Shipped Date | R3: Tracking Number | S3: Notes | T3: Return Status | U3: RMA Number | V3: Return Reason
A4: #1111 | B4: 2026-04-10 | C4: Shopify | D4: #1111 | E4: Annmarie Kennedy | G4: LILA-001 | H4: 1 | I4: 1037.27 | J4: USD | K4: Open | L4: Paid | M4: Unfulfilled | S4: U.S. Free Shipping
A5: #1110 | B5: 2026-04-10 | C5: Shopify | D5: #1110 | E5: Phayvanh Nanthavongdouangsy | G5: LILA-001 | H5: 1 | I5: 1016.36 | J5: USD | K5: Open | L5: Paid | M5: Unfulfilled | S5: U.S. Free Shipping
A6: #1109 | B6: 2026-04-09 | C6: Shopify | D6: #1109 | E6: Sarah Harris | G6: LILA-001 | H6: 1 | I6: 1016.08 | J6: USD | K6: Open | L6: Paid | M6: Unfulfilled | S6: U.S. Free Shipping
A7: #1108 | B7: 2026-04-09 | C7: Shopify | D7: #1108 | E7: Kristen Pimentel | G7: LILA-001 | H7: 1 | I7: 985.23 | J7: USD | K7: Open | L7: Paid | M7: Unfulfilled | S7: U.S. Free Shipping
A8: #1107 | B8: 2026-04-07 | C8: Shopify | D8: #1107 | E8: Louis DiPalma | F8: ljdpdm@me.com | G8: LILA-001 | H8: 1 | I8: 1043.06 | J8: USD | K8: Open | L8: Paid | M8: Unfulfilled | S8: U.S. Free Shipping
A9: #1106 | B9: 2026-04-07 | C9: Shopify | D9: #1106 | E9: Pedrum | G9: LILA-001 | H9: 1 | I9: 0 | J9: USD | K9: Delivered | L9: Paid | M9: Fulfilled | Q9: 2026-04-07 | S9: U.S. Free Shipping
A10: #1105 | B10: 2026-04-07 | C10: Shopify | D10: #1105 | E10: Pedrum | G10: LILA-001 | H10: 1 | I10: 0 | J10: CAD | K10: Delivered | L10: Paid | M10: Fulfilled | Q10: 2026-04-07 | S10: Canpar Ground
A11: #1104 | B11: 2026-03-31 | C11: Shopify | D11: #1104 | E11: Katrina Dowd | F11: katrinadowd83@gmail.com | G11: LILA-001 | H11: 1 | I11: 1302.95 | J11: USD | K11: Open | L11: Paid | M11: Unfulfilled | S11: Standard International
A12: #1103 | B12: 2026-03-27 | C12: Shopify | D12: #1103 | E12: Angela Findlay | F12: fireandprose17@outlook.com | G12: LILA-001 | H12: 1 | I12: 42.38 | J12: USD | K12: Open | L12: Paid | M12: Unfulfilled | S12: Standard
A13: #1102 | B13: 2026-03-27 | C13: Shopify | D13: #1102 | E13: Matthew Mossey | G13: LILA-001 | H13: 1 | I13: 43.74 | J13: USD | K13: Delivered | L13: Paid | M13: Fulfilled | Q13: 2026-03-27 | S13: Standard | Open ticket HS-0048: Machine crack (P100 needed)
A14: #1101 | B14: 2026-03-26 | C14: Shopify | D14: #1101 | E14: Pedrum | G14: LILA-001 | H14: 1 | I14: 0 | J14: USD | K14: Delivered | L14: Paid | M14: Fulfilled | Q14: 2026-03-26 | S14: Standard
A15: #1100 | B15: 2026-03-26 | C15: Shopify | D15: #1100 | E15: Elizabeth Antony | G15: LILA-001 | H15: 1 | I15: 131.25 | J15: USD | K15: Delivered | L15: Paid | M15: Fulfilled | Q15: 2026-03-26 | S15: Standard
A16: #1099 | B16: 2026-03-23 | C16: Shopify | D16: #1099 | E16: Tara Dupper | F16: Tarajdupper@gmail.com | G16: LILA-001 | H16: 1 | I16: 1351.87 | J16: USD | K16: Open | L16: Paid | M16: Unfulfilled | S16: Standard International
A17: #1098 | B17: 2026-03-22 | C17: Shopify | D17: #1098 | E17: Lisa Clarke | F17: lisaclarkewell@gmail.com | G17: LILA-001 | H17: 1 | I17: 127.13 | J17: USD | K17: Open | L17: Paid | M17: Unfulfilled | S17: Standard
A18: #1097 | B18: 2026-03-22 | C18: Shopify | D18: #1097 | E18: Cole Perkins | F18: cperkins39741@gmail.com | G18: LILA-001 | H18: 1 | I18: 1372.36 | J18: USD | K18: Open | L18: Paid | M18: Unfulfilled | S18: Standard International
A19: #1096 | B19: 2026-03-22 | C19: Shopify | D19: #1096 | E19: Rebecca Campbell | F19: campbellra652@gmail.com | G19: LILA-001 | H19: 1 | I19: 19.95 | J19: USD | K19: Open | L19: Paid | M19: Unfulfilled | S19: Standard
A20: #1095 | B20: 2026-03-21 | C20: Shopify | D20: #1095 | E20: Jacob Wenger | F20: wenger.jake@gmail.com | G20: LILA-001 | H20: 1 | I20: 1372.36 | J20: USD | K20: Open | L20: Paid | M20: Unfulfilled | S20: Standard International
A21: #1094 | B21: 2026-03-19 | C21: Shopify | D21: #1094 | E21: Ashley Wright | G21: LILA-001 | H21: 1 | I21: 1502.89 | J21: USD | K21: Open | L21: Paid | M21: Unfulfilled | S21: Standard
A22: #1093 | B22: 2026-03-18 | C22: Shopify | D22: #1093 | E22: Brent Neave | F22: brent@baker-neave.com | G22: LILA-001 | H22: 1 | I22: 1396.49 | J22: USD | K22: Open | L22: Paid | M22: Unfulfilled | S22: Standard
A23: #1092 | B23: 2026-03-16 | C23: Shopify | D23: #1092 | E23: Dale Bober | F23: dalebober@gmail.com | G23: LILA-001 | H23: 1 | I23: 1346.46 | J23: USD | K23: Open | L23: Paid | M23: Unfulfilled | S23: Standard International
A24: #1091 | B24: 2026-03-16 | C24: Shopify | D24: #1091 | E24: Scott Iles | F24: mrscottg@gmail.com | G24: LILA-001 | H24: 1 | I24: 19.78 | J24: USD | K24: Open | L24: Paid | M24: Unfulfilled | Q24: 2026-03-05 | R24: D420352470001907601001 | S24: Standard
A25: #1090 | B25: 2026-03-14 | C25: Shopify | D25: #1090 | E25: Rick Stauffer | F25: rick@freshveggie.com | G25: LILA-001 | H25: 1 | I25: 1351.17 | J25: USD | K25: Open | L25: Paid | M25: Unfulfilled | S25: Standard International
A26: #1089 | B26: 2026-03-13 | C26: Shopify | D26: #1089 | E26: Pedrum Amin | G26: LILA-001 | H26: 1 | I26: 0 | J26: USD | K26: Delivered | L26: Paid | M26: Fulfilled | Q26: 2026-03-13 | S26: Standard
A27: #1088 | B27: 2026-03-11 | C27: Shopify | D27: #1088 | E27: Antonio Cernuto | F27: antonio@pur2o.com | G27: LILA-001 | H27: 1 | I27: 1336.32 | J27: USD | K27: Open | L27: Paid | M27: Unfulfilled | S27: Standard International
A28: #1087 | B28: 2026-03-06 | C28: Shopify | D28: #1087 | E28: Rashida Lee | F28: happy1today@gmail.com | G28: LILA-001 | H28: 1 | I28: 999.61 | J28: USD | K28: Delivered | L28: Paid | M28: Fulfilled | Q28: 2026-03-06 | R28: 1ZV56D26DK14619146 | S28: Standard International
A29: #1086 | B29: 2026-02-28 | C29: Shopify | D29: #1086 | E29: Jean Cotis | F29: designerjeanssalon@yahoo.com | G29: LILA-001 | H29: 1 | I29: 1023.44 | J29: USD | K29: Delivered | L29: Paid | M29: Fulfilled | Q29: 2026-02-28 | R29: 1ZV56D26DK21357951 | S29: Standard International
A30: #1085 | B30: 2026-02-28 | C30: Shopify | D30: #1085 | E30: Frederick Whittington | F30: fawjr61@gmail.com | G30: LILA-001 | H30: 1 | I30: 1023.44 | J30: USD | K30: Delivered | L30: Paid | M30: Fulfilled | Q30: 2026-02-28 | R30: 1ZV56D26DK26329419 | S30: Standard International
A31: #1084 | B31: 2026-02-27 | C31: Shopify | D31: #1084 | E31: Justin Plumley | F31: jplumley6@yahoo.com | G31: LILA-001 | H31: 1 | I31: 1022.27 | J31: USD | K31: Delivered | L31: Paid | M31: Fulfilled | Q31: 2026-02-27 | R31: 1ZV56D26DK25313599 | S31: Standard International
A32: #1083 | B32: 2026-02-27 | C32: Shopify | D32: #1083 | E32: Matthew Mossey | G32: LILA-001 | H32: 1 | I32: 43.74 | J32: USD | K32: Delivered | L32: Paid | M32: Fulfilled | Q32: 2026-02-27 | S32: Standard | Open ticket HS-0048: Machine crack (P100 needed)
A33: #1082 | B33: 2026-02-26 | C33: Shopify | D33: #1082 | E33: Richard Ahola | G33: LILA-001 | H33: 1 | I33: 1129.99 | J33: USD | K33: Delivered | L33: Paid | M33: Fulfilled | Q33: 2026-02-26 | S33: Standard
A34: #1081 | B34: 2026-02-25 | C34: Shopify | D34: #1081 | E34: Elizabeth Antony | G34: LILA-001 | H34: 1 | I34: 131.25 | J34: USD | K34: Delivered | L34: Paid | M34: Fulfilled | Q34: 2026-02-25 | S34: Standard
A35: #1080 | B35: 2026-02-25 | C35: Shopify | D35: #1080 | E35: AUDREY BALANAY-ST JOHN | F35: audreystjohn143@gmail.com | G35: LILA-001 | H35: 1 | I35: 1007.06 | J35: USD | K35: Delivered | L35: Paid | M35: Fulfilled | Q35: 2026-02-25 | R35: 1ZV56D26DK23942494 | S35: Standard International
A36: #1079 | B36: 2026-02-25 | C36: Shopify | D36: #1079 | E36: Michael Romans | F36: xseaman@msn.com | G36: LILA-001 | H36: 1 | I36: 1026.43 | J36: USD | K36: Delivered | L36: Paid | M36: Fulfilled | Q36: 2026-02-25 | R36: 1ZV56D26DK28560325 | S36: Standard International
A37: #1078 | B37: 2026-02-24 | C37: Shopify | D37: #1078 | E37: Suzan Jackovatz | F37: suzan@jackovatz.com | G37: LILA-001 | H37: 1 | I37: 1008.01 | J37: USD | K37: Delivered | L37: Paid | M37: Fulfilled | Q37: 2026-02-24 | R37: 1ZV56D26DK04334507 | S37: Standard International
A38: #1077 | B38: 2026-02-23 | C38: Shopify | D38: #1077 | E38: Dixie Bean | F38: dixbean@yahoo.com | G38: LILA-001 | H38: 1 | I38: 1006.76 | J38: USD | K38: Delivered | L38: Paid | M38: Fulfilled | Q38: 2026-02-23 | R38: 1ZV56D26DK18155292 | S38: Standard International
A39: #1076 | B39: 2026-02-23 | C39: Shopify | D39: #1076 | E39: Joy Seargeant | F39: thejosierave@hotmail.com | G39: LILA-001 | H39: 1 | I39: 1107.39 | J39: USD | K39: Delivered | L39: Paid | M39: Fulfilled | Q39: 2026-02-23 | R39: D420352470001966966001 | S39: Standard
A40: #1075 | B40: 2026-02-22 | C40: Shopify | D40: #1075 | E40: Ann Prendergast | F40: evirdhgih@gmail.com | G40: LILA-001 | H40: 1 | I40: 1049.99 | J40: USD | K40: Open | L40: Paid | M40: Unfulfilled | S40: Standard
A41: #1074 | B41: 2026-02-22 | C41: Shopify | D41: #1074 | E41: Sandra Sweet | F41: Shschestnut@gmail.com | G41: LILA-001 | H41: 1 | I41: 1026.36 | J41: USD | K41: Delivered | L41: Paid | M41: Fulfilled | Q41: 2026-02-22 | R41: 1ZV56D26DK09789697 | S41: Standard International
A42: #1073 | B42: 2026-02-22 | C42: Shopify | D42: #1073 | E42: Karon Plasha | F42: kfplasha@icloud.com | G42: LILA-001 | H42: 1 | I42: 1005.96 | J42: USD | K42: Delivered | L42: Paid | M42: Fulfilled | Q42: 2026-02-22 | R42: 1ZV56D26DK36337632 | S42: Standard International
A43: #1072 | B43: 2026-02-19 | C43: Shopify | D43: #1072 | E43: Robert Simoneau | F43: robert@akamna.com | G43: LILA-001 | H43: 1 | I43: 1028.99 | J43: USD | K43: Delivered | L43: Paid | M43: Fulfilled | Q43: 2026-02-19 | R43: D556276790000035134001 | S43: Standard
A44: #1071 | B44: 2026-02-18 | C44: Shopify | D44: #1071 | E44: Anthony kurt | F44: tnykurt313@yahoo.com | G44: LILA-001 | H44: 1 | I44: 1006.97 | J44: USD | K44: Delivered | L44: Paid | M44: Fulfilled | Q44: 2026-02-18 | R44: 1ZV56D26DK37674810 | S44: Standard International | Open ticket HS-0075: Top lid cracked (replacement needed)
A45: #1070 | B45: 2026-02-18 | C45: Shopify | D45: #1070 | E45: ron russell | F45: ron@newcmi.ca | G45: LILA-001 | H45: 1 | I45: 1049.99 | J45: USD | K45: Open | L45: Paid | M45: Unfulfilled | S45: Standard
A46: #1069 | B46: 2026-02-16 | C46: Shopify | D46: #1069 | E46: Robert Buckley | F46: robert.daniel.buckley@gmail.com | G46: LILA-001 | H46: 1 | I46: 1001.65 | J46: USD | K46: Delivered | L46: Paid | M46: Fulfilled | Q46: 2026-02-16 | R46: 1ZV56D26DK01309291 | S46: Standard International
A47: #1068 | B47: 2026-02-15 | C47: Shopify | D47: #1068 | E47: Fred Rice | F47: ricefj50@yahoo.com | G47: LILA-001 | H47: 1 | I47: 1024.49 | J47: USD | K47: Delivered | L47: Paid | M47: Fulfilled | Q47: 2026-02-15 | R47: 1ZV56D26DK37984360 | S47: Standard International
A48: #1067 | B48: 2026-02-13 | C48: Shopify | D48: #1067 | E48: Scott Gilbert | F48: mrscottg@gmail.com | G48: LILA-001 | H48: 1 | I48: 1049.99 | J48: USD | K48: Delivered | L48: Paid | M48: Fulfilled | Q48: 2026-02-13 | R48: D420352470001907601001 | S48: Standard
A49: #1066 | B49: 2026-02-13 | C49: Shopify | D49: #1066 | E49: Melissa Braschuk | G49: LILA-001 | H49: 1 | I49: 43.74 | J49: USD | K49: Delivered | L49: Paid | M49: Fulfilled | Q49: 2026-02-13 | S49: Standard
A50: #1065 | B50: 2026-02-13 | C50: Shopify | D50: #1065 | E50: Tricia Bowling | F50: Triciab12@gmail.com | G50: LILA-001 | H50: 1 | I50: 1001.48 | J50: USD | K50: Delivered | L50: Paid | M50: Fulfilled | Q50: 2026-02-13 | R50: 1ZV56D26DK06672193 | S50: Standard International | Open ticket HS-0076: Machine flashing issue
A51: #1064 | B51: 2026-02-13 | C51: Shopify | D51: #1064 | E51: Joseph Le | G51: LILA-001 | H51: 0 | I51: 0 | J51: USD | K51: Cancelled | L51: Refunded | M51: Unfulfilled | S51: Standard International
A52: #1063 | B52: 2026-02-12 | C52: Shopify | D52: #1063 | E52: Jeremiah Pauw | F52: jeremiah@peacockhospitality.ca | G52: LILA-001 | H52: 1 | I52: 1028.99 | J52: USD | K52: Delivered | L52: Paid | M52: Fulfilled | Q52: 2026-02-12 | R52: D420352470001907597001 | S52: Standard
A53: #1062 | B53: 2026-02-10 | C53: Shopify | D53: #1062 | E53: Douglas Hanson | F53: dhanson7298@gmail.com | G53: LILA-001 | H53: 1 | I53: 996.07 | J53: USD | K53: Delivered | L53: Paid | M53: Fulfilled | Q53: 2026-02-10 | R53: 1ZV56D26DK34315829 | S53: Standard International | Open ticket HS-0077: Back lid/power button issue

Sheet Inventory
A1: Inventory Management
A2: Real-time stock levels across all locations | J2: Status: OK / LOW / OUT (auto-calculated)
A3: SKU | B3: Product Name | C3: Category | D3: Location | E3: On Hand Qty | F3: Committed Qty | G3: Available Qty | H3: Expected Qty | I3: Reorder Point | J3: Stock Status | K3: Unit Cost | L3: Total Value | M3: Batch/Lot # | N3: Expiry Date | O3: Last Updated | P3: Notes | Q3: Lead Time (days) | R3: Reorder Qty | S3: Safety Stock | T3: Days on Hand | U3: Reorder Alert
A4: VH-100 | B4: Virgo Smart Hub | C4: Smart Home | D4: Toronto-01 | E4: 150 | F4: 7 | G4: =E4-F4 -> 143 | H4: 50 | I4: 25 | J4: =IF(G4<=0,"OUT",IF(G4<=I4,"LOW","OK")) -> OK | K4: 85 | L4: =E4*K4 -> 12750 | M4: LOT-2026-041 | N4: 2028-04-01 | O4: 2026-04-10 | Q4: 14 | R4: 50 | S4: 10 | T4: =IF(F4=0,"N/A",ROUND(E4/(F4/7),0)) -> 150 | U4: =IF(G4<=0,"ORDER NOW",IF(G4<=I4,"REORDER","OK")) -> OK
A5: VH-200 | B5: Virgo Motion Sensor | C5: Sensors | D5: Toronto-01 | E5: 320 | F5: 13 | G5: =E5-F5 -> 307 | H5: 100 | I5: 50 | J5: =IF(G5<=0,"OUT",IF(G5<=I5,"LOW","OK")) -> OK | K5: 32 | L5: =E5*K5 -> 10240 | M5: LOT-2026-038 | N5: 2029-01-01 | O5: 2026-04-10 | Q5: 10 | R5: 100 | S5: 20 | T5: =IF(F5=0,"N/A",ROUND(E5/(F5/7),0)) -> 172 | U5: =IF(G5<=0,"ORDER NOW",IF(G5<=I5,"REORDER","OK")) -> OK
A6: VH-300 | B6: Virgo Security Cam | C6: Security | D6: Toronto-01 | E6: 80 | F6: 10 | G6: =E6-F6 -> 70 | H6: 0 | I6: 30 | J6: =IF(G6<=0,"OUT",IF(G6<=I6,"LOW","OK")) -> OK | K6: 120 | L6: =E6*K6 -> 9600 | M6: LOT-2026-035 | N6: 2028-06-01 | O6: 2026-04-10 | P6: Order more from supplier | Q6: 21 | R6: 30 | S6: 10 | T6: =IF(F6=0,"N/A",ROUND(E6/(F6/7),0)) -> 56 | U6: =IF(G6<=0,"ORDER NOW",IF(G6<=I6,"REORDER","OK")) -> OK
A7: VH-400 | B7: Virgo Door Lock | C7: Access | D7: Toronto-01 | E7: 45 | F7: 8 | G7: =E7-F7 -> 37 | H7: 25 | I7: 20 | J7: =IF(G7<=0,"OUT",IF(G7<=I7,"LOW","OK")) -> OK | K7: 95 | L7: =E7*K7 -> 4275 | M7: LOT-2026-040 | N7: 2028-12-01 | O7: 2026-04-10 | Q7: 18 | R7: 25 | S7: 8 | T7: =IF(F7=0,"N/A",ROUND(E7/(F7/7),0)) -> 39 | U7: =IF(G7<=0,"ORDER NOW",IF(G7<=I7,"REORDER","OK")) -> OK
A8: VH-100 | B8: Virgo Smart Hub | C8: Smart Home | D8: Vancouver-01 | E8: 60 | F8: 2 | G8: =E8-F8 -> 58 | H8: 0 | I8: 15 | J8: =IF(G8<=0,"OUT",IF(G8<=I8,"LOW","OK")) -> OK | K8: 85 | L8: =E8*K8 -> 5100 | M8: LOT-2026-039 | N8: 2028-04-01 | O8: 2026-04-10 | Q8: 14 | R8: 30 | S8: 5 | T8: =IF(F8=0,"N/A",ROUND(E8/(F8/7),0)) -> 210 | U8: =IF(G8<=0,"ORDER NOW",IF(G8<=I8,"REORDER","OK")) -> OK
A9: VH-500 | B9: Virgo Thermostat | C9: Climate | D9: Toronto-01 | E9: 10 | F9: 0 | G9: =E9-F9 -> 10 | H9: 50 | I9: 25 | J9: =IF(G9<=0,"OUT",IF(G9<=I9,"LOW","OK")) -> LOW | K9: 68 | L9: =E9*K9 -> 680 | M9: LOT-2026-042 | N9: 2029-03-01 | O9: 2026-04-10 | P9: LOW - PO submitted | Q9: 12 | R9: 50 | S9: 10 | T9: =IF(F9=0,"N/A",ROUND(E9/(F9/7),0)) -> N/A | U9: =IF(G9<=0,"ORDER NOW",IF(G9<=I9,"REORDER","OK")) -> REORDER

Sheet Make Orders
A1: Make Order Management
A2: Manufacturing & production order tracking
A3: MO Number | B3: Created Date | C3: Product SKU | D3: Product Name | E3: BOM Version | F3: Qty to Make | G3: Qty Completed | H3: % Complete | I3: Start Date | J3: Status | K3: Due Date | L3: Assigned To | M3: Materials Status | N3: Labor Hours (Est) | O3: Labor Hours (Actual) | P3: Production Notes | Q3: Linked SO | R3: Warehouse
A4: MO-001 | B4: 2026-04-08 | C4: VH-100 | D4: Virgo Smart Hub | E4: v2.1 | F4: 5 | G4: 0 | H4: =G4/F4 -> 0 | I4: 2026-04-10 | J4: Planned | K4: 2026-04-14 | L4: Line A Team | M4: Available | N4: 10 | O4: 0 | P4: Waiting for production slot | Q4: SO-001 | R4: Toronto-01
A5: MO-002 | B5: 2026-04-09 | C5: VH-300 | D5: Virgo Security Cam | E5: v1.3 | F5: 10 | G5: 3 | H5: =G5/F5 -> 0.3 | I5: 2026-04-09 | J5: In Progress | K5: 2026-04-16 | L5: Line B Team | M5: Partial | N5: 25 | O5: 8 | P5: 3 units completed, waiting on lens modules | Q5: SO-002 | R5: Toronto-01
A6: MO-003 | B6: 2026-04-05 | C6: VH-200 | D6: Virgo Motion Sensor | E6: v3.0 | F6: 100 | G6: 100 | H6: =G6/F6 -> 1 | I6: 2026-04-05 | J6: Completed | K6: 2026-04-09 | L6: Line A Team | M6: Complete | N6: 15 | O6: 14 | P6: Batch complete, QC passed | R6: Toronto-01
A7: MO-004 | B7: 2026-04-10 | C7: VH-500 | D7: Virgo Thermostat | E7: v1.0 | F7: 50 | G7: 0 | H7: =G7/F7 -> 0 | I7: 2026-04-12 | J7: Planned | K7: 2026-04-22 | L7: Line C Team | M7: Awaiting PO | N7: 30 | O7: 0 | P7: Materials on PO-005 due Apr 14 | R7: Toronto-01

Sheet Vendors & POs
A1: Vendor Sourcing & Purchase Orders
A2: Supplier management, PO tracking, landed costs
A3: PO Number | B3: PO Date | C3: Vendor Name | D3: Vendor Contact | E3: Vendor Email | F3: Item SKU | G3: Item Description | H3: Qty Ordered | I3: Unit Cost | J3: Currency | K3: Total Cost | L3: PO Status | M3: Expected Delivery | N3: Actual Delivery | O3: Lead Time (days) | P3: Payment Terms | Q3: Freight Cost | R3: Landed Cost/Unit | S3: Quality Rating | T3: Notes | U3: Qty Received | V3: Receipt Variance | W3: Days Overdue
A4: PO-001 | B4: 2026-04-01 | C4: ShenZhen Electronics Co | D4: Li Wei | E4: li@szelectronics.cn | F4: VH-100-PCB | G4: Smart Hub PCB Assembly | H4: 200 | I4: 22.5 | J4: USD | K4: =H4*I4 -> 4500 | L4: Received | M4: 2026-04-08 | N4: 2026-04-07 | O4: =N4-B4 -> 6 | P4: Net 30 | Q4: 450 | R4: =(K4+Q4)/H4 -> 24.75 | S4: 4.5 | T4: Quality consistent | U4: 200 | V4: =U4-H4 -> 0 | W4: =IF(L4="Received",0,IF(TODAY()>M4,TODAY()-M4,0)) -> 0
A5: PO-002 | B5: 2026-04-02 | C5: OptiLens Taiwan | D5: Chen Yu | E5: chen@optilens.tw | F5: VH-300-LENS | G5: Camera Lens Module | H5: 100 | I5: 18 | J5: USD | K5: =H5*I5 -> 1800 | L5: In Transit | M5: 2026-04-12 | O5: =IF(N5="",M5-B5,N5-B5) -> 10 | P5: Net 45 | Q5: 280 | R5: =(K5+Q5)/H5 -> 20.8 | S5: 4.2 | U5: 0 | V5: =U5-H5 -> -100 | W5: =IF(L5="Received",0,IF(TODAY()>M5,TODAY()-M5,0)) -> 0
A6: PO-003 | B6: 2026-04-03 | C6: Canadian Plastics Inc | D6: Marie Dupont | E6: marie@canplastics.ca | F6: VH-ENC-01 | G6: Device Enclosures (assorted) | H6: 500 | I6: 4.75 | J6: CAD | K6: =H6*I6 -> 2375 | L6: Open | M6: 2026-04-20 | O6: =IF(N6="",M6-B6,N6-B6) -> 17 | P6: Net 30 | Q6: 120 | R6: =(K6+Q6)/H6 -> 4.99 | S6: 4 | T6: Local supplier | U6: 0 | V6: =U6-H6 -> -500 | W6: =IF(L6="Received",0,IF(TODAY()>M6,TODAY()-M6,0)) -> 0
A7: PO-004 | B7: 2026-04-05 | C7: BatteryWorld Ltd | D7: James Park | E7: james@battworld.com | F7: VH-BAT-LI | G7: Li-Ion Battery Pack 3.7V | H7: 300 | I7: 6.2 | J7: USD | K7: =H7*I7 -> 1860 | L7: Open | M7: 2026-04-22 | O7: =IF(N7="",M7-B7,N7-B7) -> 17 | P7: Net 30 | Q7: 180 | R7: =(K7+Q7)/H7 -> 6.8 | S7: 3.8 | T7: New supplier, trial order | U7: 0 | V7: =U7-H7 -> -300 | W7: =IF(L7="Received",0,IF(TODAY()>M7,TODAY()-M7,0)) -> 0
A8: PO-005 | B8: 2026-04-08 | C8: ThermoComp GmbH | D8: Klaus Müller | E8: klaus@thermocomp.de | F8: VH-500-CTRL | G8: Thermostat Controller Board | H8: 50 | I8: 35 | J8: EUR | K8: =H8*I8 -> 1750 | L8: Open | M8: 2026-04-21 | O8: =IF(N8="",M8-B8,N8-B8) -> 13 | P8: Net 60 | Q8: 320 | R8: =(K8+Q8)/H8 -> 41.4 | S8: 4.7 | T8: Premium supplier for MO-004 | U8: 0 | V8: =U8-H8 -> -50 | W8: =IF(L8="Received",0,IF(TODAY()>M8,TODAY()-M8,0)) -> 0

Sheet BOMs
A1: Bill of Materials (BOM) Management
A2: Multi-level BOMs with cost rollups and version control
A3: BOM ID | B3: Product SKU | C3: Product Name | D3: BOM Version | E3: Level | F3: Component SKU | G3: Component Name | H3: Qty Per Unit | I3: Unit of Measure | J3: Component Cost | K3: Extended Cost | L3: Supplier | M3: Lead Time (days) | N3: Wastage % | O3: Effective Date | P3: Status | Q3: Notes | R3: Parent Assembly | S3: Adjusted Qty (w/ Waste)
A4: BOM-001 | B4: VH-100 | C4: Virgo Smart Hub | D4: v2.1 | E4: 0 | F4: — | G4: — FINISHED GOOD — | H4: 1 | I4: EA | K4: =SUM(K5:K10) -> 43.95 | O4: 2026-03-01 | P4: Active | Q4: Main product BOM | R4: — | S4: =IF(N4="",H4,ROUND(H4/(1-N4/100),2)) -> 1
A5: BOM-001 | B5: VH-100 | C5: Virgo Smart Hub | D5: v2.1 | E5: 1 | F5: VH-100-PCB | G5: Smart Hub PCB Assembly | H5: 1 | I5: EA | J5: 22.5 | K5: =H5*J5 -> 22.5 | L5: ShenZhen Electronics | M5: 14 | N5: 2 | O5: 2026-03-01 | P5: Active | R5: VH-100 | S5: =IF(N5="",H5,ROUND(H5/(1-N5/100),2)) -> 1.02
A6: BOM-001 | B6: VH-100 | C6: Virgo Smart Hub | D6: v2.1 | E6: 1 | F6: VH-ENC-01 | G6: Device Enclosure | H6: 1 | I6: EA | J6: 4.75 | K6: =H6*J6 -> 4.75 | L6: Canadian Plastics | M6: 7 | N6: 1 | O6: 2026-03-01 | P6: Active | R6: VH-100 | S6: =IF(N6="",H6,ROUND(H6/(1-N6/100),2)) -> 1.01
A7: BOM-001 | B7: VH-100 | C7: Virgo Smart Hub | D7: v2.1 | E7: 1 | F7: VH-BAT-LI | G7: Li-Ion Battery Pack | H7: 1 | I7: EA | J7: 6.2 | K7: =H7*J7 -> 6.2 | L7: BatteryWorld | M7: 10 | N7: 1 | O7: 2026-03-01 | P7: Active | R7: VH-100 | S7: =IF(N7="",H7,ROUND(H7/(1-N7/100),2)) -> 1.01
A8: BOM-001 | B8: VH-100 | C8: Virgo Smart Hub | D8: v2.1 | E8: 1 | F8: VH-ANT-WIFI | G8: WiFi Antenna Module | H8: 1 | I8: EA | J8: 3.8 | K8: =H8*J8 -> 3.8 | L8: ShenZhen Electronics | M8: 14 | N8: 1 | O8: 2026-03-01 | P8: Active | R8: VH-100 | S8: =IF(N8="",H8,ROUND(H8/(1-N8/100),2)) -> 1.01
A9: BOM-001 | B9: VH-100 | C9: Virgo Smart Hub | D9: v2.1 | E9: 1 | F9: VH-PWR-USB | G9: USB-C Power Supply | H9: 1 | I9: EA | J9: 5.5 | K9: =H9*J9 -> 5.5 | L9: BatteryWorld | M9: 7 | N9: 0 | O9: 2026-03-01 | P9: Active | R9: VH-100 | S9: =IF(N9="",H9,ROUND(H9/(1-N9/100),2)) -> 1
A10: BOM-001 | B10: VH-100 | C10: Virgo Smart Hub | D10: v2.1 | E10: 1 | F10: VH-LBL-100 | G10: Product Label & Packaging | H10: 1 | I10: EA | J10: 1.2 | K10: =H10*J10 -> 1.2 | L10: Canadian Plastics | M10: 3 | N10: 5 | O10: 2026-03-01 | P10: Active | R10: VH-100 | S10: =IF(N10="",H10,ROUND(H10/(1-N10/100),2)) -> 1.05
A11: BOM-002 | B11: VH-300 | C11: Virgo Security Cam | D11: v1.3 | E11: 0 | F11: — | G11: — FINISHED GOOD — | H11: 1 | I11: EA | K11: =SUM(K12:K15) -> 58.7 | O11: 2026-02-15 | P11: Active | R11: — | S11: =IF(N11="",H11,ROUND(H11/(1-N11/100),2)) -> 1
A12: BOM-002 | B12: VH-300 | C12: Virgo Security Cam | D12: v1.3 | E12: 1 | F12: VH-300-PCB | G12: Camera PCB Assembly | H12: 1 | I12: EA | J12: 28 | K12: =H12*J12 -> 28 | L12: ShenZhen Electronics | M12: 14 | N12: 2 | O12: 2026-02-15 | P12: Active | R12: VH-300 | S12: =IF(N12="",H12,ROUND(H12/(1-N12/100),2)) -> 1.02
A13: BOM-002 | B13: VH-300 | C13: Virgo Security Cam | D13: v1.3 | E13: 1 | F13: VH-300-LENS | G13: Camera Lens Module | H13: 1 | I13: EA | J13: 18 | K13: =H13*J13 -> 18 | L13: OptiLens Taiwan | M13: 21 | N13: 1 | O13: 2026-02-15 | P13: Active | R13: VH-300 | S13: =IF(N13="",H13,ROUND(H13/(1-N13/100),2)) -> 1.01
A14: BOM-002 | B14: VH-300 | C14: Virgo Security Cam | D14: v1.3 | E14: 1 | F14: VH-ENC-03 | G14: Camera Enclosure (weatherproof) | H14: 1 | I14: EA | J14: 8.5 | K14: =H14*J14 -> 8.5 | L14: Canadian Plastics | M14: 7 | N14: 2 | O14: 2026-02-15 | P14: Active | R14: VH-300 | S14: =IF(N14="",H14,ROUND(H14/(1-N14/100),2)) -> 1.02
A15: BOM-002 | B15: VH-300 | C15: Virgo Security Cam | D15: v1.3 | E15: 1 | F15: VH-IR-LED | G15: IR LED Array (night vision) | H15: 1 | I15: EA | J15: 4.2 | K15: =H15*J15 -> 4.2 | L15: ShenZhen Electronics | M15: 14 | N15: 1 | O15: 2026-02-15 | P15: Active | R15: VH-300 | S15: =IF(N15="",H15,ROUND(H15/(1-N15/100),2)) -> 1.01

Sheet Serial Tracker
A1: Serial Number Tracker — LILA Pro
A2: Full registry: 450 units across 5 batches | LL01-XXXXXXXXXXX format
A4: Batch Summary
A5: Batch | B5: Serial Range | C5: Total Units | D5: Shipped | E5: In Stock | F5: Ship Rate %
A6: P50 | B6: LL01-00000000001 to LL01-00000000050 | C6: 50 | D6: =COUNTIFS(C14:C463,A6,L14:L463,"<>In Stock") -> 2 | E6: =C6-D6 -> 48 | F6: =IF(C6=0,0,ROUND(D6/C6*100,1)) -> 4
A7: P150 | B7: LL01-00000000051 to LL01-00000000200 | C7: 150 | D7: =COUNTIFS(C14:C463,A7,L14:L463,"<>In Stock") -> 6 | E7: =C7-D7 -> 144 | F7: =IF(C7=0,0,ROUND(D7/C7*100,1)) -> 4
A8: P50N | B8: LL01-00000000201 to LL01-00000000250 | C8: 50 | D8: =COUNTIFS(C14:C463,A8,L14:L463,"<>In Stock") -> 31 | E8: =C8-D8 -> 19 | F8: =IF(C8=0,0,ROUND(D8/C8*100,1)) -> 62
A9: P100 | B9: LL01-00000000251 to LL01-00000000350 | C9: 100 | D9: =COUNTIFS(C14:C463,A9,L14:L463,"<>In Stock") -> 0 | E9: =C9-D9 -> 100 | F9: =IF(C9=0,0,ROUND(D9/C9*100,1)) -> 0
A10: P100X | B10: LL01-00000000351 to LL01-00000000450 | C10: 100 | D10: =COUNTIFS(C14:C463,A10,L14:L463,"<>In Stock") -> 0 | E10: =C10-D10 -> 100 | F10: =IF(C10=0,0,ROUND(D10/C10*100,1)) -> 0
A11: TOTAL | B11: LL01-00000000001 to LL01-00000000450 | C11: =SUM(C6:C10) -> 450 | D11: =SUM(D6:D10) -> 39 | E11: =SUM(E6:E10) -> 411 | F11: =IF(C11=0,0,ROUND(D11/C11*100,1)) -> 8.7
A13: Serial Number | B13: SKU | C13: Batch/Lot | D13: Batch Seq # | E13: Manufacture Date | F13: Ship Date | G13: Customer Name | H13: Customer Phone | I13: Destination | J13: Carrier | K13: Tracking Number | L13: Status | M13: Shipment ID | N13: HubSpot Ticket | O13: Warranty Expiry
A14: LL01-00000000001 | B14: LILA-001 | C14: P50 | D14: 1 | L14: In Stock
A15: LL01-00000000002 | B15: LILA-001 | C15: P50 | D15: 2 | L15: In Stock
A16: LL01-00000000003 | B16: LILA-001 | C16: P50 | D16: 3 | L16: In Stock
A17: LL01-00000000004 | B17: LILA-001 | C17: P50 | D17: 4 | L17: In Stock
A18: LL01-00000000005 | B18: LILA-001 | C18: P50 | D18: 5 | F18: 2026-04-10 | G18: Mary Oskamp | H18: 905-536-6985 | I18: 12 Pulla Street, Trenton, ON, K8V 5P7 | J18: Canpar | K18: D420352470002041843001 | L18: In Transit | M18: SHP-CA-038 | O18: =F18+730 -> 46852
A19: LL01-00000000006 | B19: LILA-001 | C19: P50 | D19: 6 | L19: In Stock
A20: LL01-00000000007 | B20: LILA-001 | C20: P50 | D20: 7 | L20: In Stock
A21: LL01-00000000008 | B21: LILA-001 | C21: P50 | D21: 8 | L21: In Stock
A22: LL01-00000000009 | B22: LILA-001 | C22: P50 | D22: 9 | L22: In Stock
A23: LL01-00000000010 | B23: LILA-001 | C23: P50 | D23: 10 | L23: In Stock
A24: LL01-00000000011 | B24: LILA-001 | C24: P50 | D24: 11 | L24: In Stock
A25: LL01-00000000012 | B25: LILA-001 | C25: P50 | D25: 12 | L25: In Stock
A26: LL01-00000000013 | B26: LILA-001 | C26: P50 | D26: 13 | L26: In Stock
A27: LL01-00000000014 | B27: LILA-001 | C27: P50 | D27: 14 | L27: In Stock
A28: LL01-00000000015 | B28: LILA-001 | C28: P50 | D28: 15 | L28: In Stock
A29: LL01-00000000016 | B29: LILA-001 | C29: P50 | D29: 16 | L29: In Stock
A30: LL01-00000000017 | B30: LILA-001 | C30: P50 | D30: 17 | L30: In Stock
... A57: LL01-00000000044 | B57: LILA-001 | C57: P50 | D57: 44 | L57: In Stock
A58: LL01-00000000045 | B58: LILA-001 | C58: P50 | D58: 45 | F58: 2026-01-30 | G58: Jason Kemp | H58: 613-791-7734 | I58: 2401 Shanna Rd, Carp, ON, K0A 1L0 | J58: Canpar | K58: D556276790000029076001 | L58: Delivered | M58: SHP-CA-002 | O58: =F58+730 -> 46782
A59: LL01-00000000046 | B59: LILA-001 | C59: P50 | D59: 46 | L59: In Stock
A60: LL01-00000000047 | B60: LILA-001 | C60: P50 | D60: 47 | L60: In Stock
A61: LL01-00000000048 | B61: LILA-001 | C61: P50 | D61: 48 | L61: In Stock
A62: LL01-00000000049 | B62: LILA-001 | C62: P50 | D62: 49 | L62: In Stock
A63: LL01-00000000050 | B63: LILA-001 | C63: P50 | D63: 50 | L63: In Stock
A64: LL01-00000000051 | B64: LILA-001 | C64: P150 | D64: 51 | L64: In Stock
A65: LL01-00000000052 | B65: LILA-001 | C65: P150 | D65: 52 | L65: In Stock
A66: LL01-00000000053 | B66: LILA-001 | C66: P150 | D66: 53 | L66: In Stock
A67: LL01-00000000054 | B67: LILA-001 | C67: P150 | D67: 54 | L67: In Stock
A68: LL01-00000000055 | B68: LILA-001 | C68: P150 | D68: 55 | L68: In Stock
A69: LL01-00000000056 | B69: LILA-001 | C69: P150 | D69: 56 | L69: In Stock
A70: LL01-00000000057 | B70: LILA-001 | C70: P150 | D70: 57 | L70: In Stock
... A121: LL01-00000000108 | B121: LILA-001 | C121: P150 | D121: 108 | L121: In Stock
A122: LL01-00000000109 | B122: LILA-001 | C122: P150 | D122: 109 | F122: 2026-03-18 | G122: Joan Teichroeb | H122: 250-961-8667 | I122: 395 Redfern Dr, Vanderhoof, BC, V0J 3A2 | J122: Canpar | K122: D556276790000042526001 | L122: Delivered | M122: SHP-CA-025 | N122: HS-0044 | O122: =F122+730 -> 46829
A123: LL01-00000000110 | B123: LILA-001 | C123: P150 | D123: 110 | L123: In Stock
A124: LL01-00000000111 | B124: LILA-001 | C124: P150 | D124: 111 | L124: In Stock
A125: LL01-00000000112 | B125: LILA-001 | C125: P150 | D125: 112 | L125: In Stock
A126: LL01-00000000113 | B126: LILA-001 | C126: P150 | D126: 113 | L126: In Stock
A127: LL01-00000000114 | B127: LILA-001 | C127: P150 | D127: 114 | L127: In Stock
A128: LL01-00000000115 | B128: LILA-001 | C128: P150 | D128: 115 | L128: In Stock
A129: LL01-00000000116 | B129: LILA-001 | C129: P150 | D129: 116 | L129: In Stock
A130: LL01-00000000117 | B130: LILA-001 | C130: P150 | D130: 117 | L130: In Stock
A131: LL01-00000000118 | B131: LILA-001 | C131: P150 | D131: 118 | L131: In Stock
A132: LL01-00000000119 | B132: LILA-001 | C132: P150 | D132: 119 | L132: In Stock
A133: LL01-00000000120 | B133: LILA-001 | C133: P150 | D133: 120 | L133: In Stock
A134: LL01-00000000121 | B134: LILA-001 | C134: P150 | D134: 121 | L134: In Stock
A135: LL01-00000000122 | B135: LILA-001 | C135: P150 | D135: 122 | F135: 2026-03-05 | G135: Scott Gilbert | H135: 780-952-9739 | I135: 5601 56a St, Beaumont, AB, T4X 1A7 | J135: Canpar | K135: D420352470001907601001 | L135: Delivered | M135: SHP-CA-023 | O135: =F135+730 -> 46816
A136: LL01-00000000123 | B136: LILA-001 | C136: P150 | D136: 123 | L136: In Stock
A137: LL01-00000000124 | B137: LILA-001 | C137: P150 | D137: 124 | L137: In Stock
A138: LL01-00000000125 | B138: LILA-001 | C138: P150 | D138: 125 | L138: In Stock
A139: LL01-00000000126 | B139: LILA-001 | C139: P150 | D139: 126 | F139: 2026-02-17 | G139: Vicki Myhre | H139: 403-901-9472 | I139: 115 Hillview Rd, Strathmore, AB, T1P 1W2 | J139: Canpar | K139: D556276790000032996001 | L139: Delivered | M139: SHP-CA-004 | O139: =F139+730 -> 46800
A140: LL01-00000000127 | B140: LILA-001 | C140: P150 | D140: 127 | L140: In Stock
A141: LL01-00000000128 | B141: LILA-001 | C141: P150 | D141: 128 | L141: In Stock
A142: LL01-00000000129 | B142: LILA-001 | C142: P150 | D142: 129 | L142: In Stock
A143: LL01-00000000130 | B143: LILA-001 | C143: P150 | D143: 130 | L143: In Stock
A144: LL01-00000000131 | B144: LILA-001 | C144: P150 | D144: 131 | L144: In Stock
A145: LL01-00000000132 | B145: LILA-001 | C145: P150 | D145: 132 | L145: In Stock
A146: LL01-00000000133 | B146: LILA-001 | C146: P150 | D146: 133 | L146: In Stock
A147: LL01-00000000134 | B147: LILA-001 | C147: P150 | D147: 134 | L147: In Stock
A148: LL01-00000000135 | B148: LILA-001 | C148: P150 | D148: 135 | L148: In Stock
A149: LL01-00000000136 | B149: LILA-001 | C149: P150 | D149: 136 | L149: In Stock
A150: LL01-00000000137 | B150: LILA-001 | C150: P150 | D150: 137 | L150: In Stock
A151: LL01-00000000138 | B151: LILA-001 | C151: P150 | D151: 138 | L151: In Stock
... A154: LL01-00000000141 | B154: LILA-001 | C154: P150 | D154: 141 | L154: In Stock
A155: LL01-00000000142 | B155: LILA-001 | C155: P150 | D155: 142 | F155: 2026-03-20 | G155: Joy Seargeant | H155: 807-630-7618 | I155: 147 Mud Lake Road, Murillo, ON, P0T 2G0 | J155: Canpar | K155: D420352470001966966001 | L155: Delivered | M155: SHP-CA-028 | O155: =F155+730 -> 46831
A156: LL01-00000000143 | B156: LILA-001 | C156: P150 | D156: 143 | L156: In Stock
A157: LL01-00000000144 | B157: LILA-001 | C157: P150 | D157: 144 | F157: 2026-02-24 | G157: Robert Simoneau | H157: 514-777-8247 | I157: 4367 Pl. Joseph-Lenoir, Saint-Laurent, QC, H4R 3C3 | J157: Canpar | K157: D556276790000035134001 | L157: Delivered | M157: SHP-CA-024 | N157: HS-0064 | O157: =F157+730 -> 46807
A158: LL01-00000000145 | B158: LILA-001 | C158: P150 | D158: 145 | F158: 2026-01-29 | G158: Amanda McCordic | H158: 506-478-4711 | I158: 16 Johnstone Ln, Charters Settlement, NB, E3C 0E3 | J158: UPS | K158: 1ZV56D26DK27263612 | L158: Delivered | M158: SHP-CA-001 | N158: HS-0045 | O158: =F158+730 -> 46781
A159: LL01-00000000146 | B159: LILA-001 | C159: P150 | D159: 146 | L159: In Stock
A160: LL01-00000000147 | B160: LILA-001 | C160: P150 | D160: 147 | L160: In Stock
A161: LL01-00000000148 | B161: LILA-001 | C161: P150 | D161: 148 | L161: In Stock
A162: LL01-00000000149 | B162: LILA-001 | C162: P150 | D162: 149 | L162: In Stock
A163: LL01-00000000150 | B163: LILA-001 | C163: P150 | D163: 150 | L163: In Stock
A164: LL01-00000000151 | B164: LILA-001 | C164: P150 | D164: 151 | L164: In Stock
A165: LL01-00000000152 | B165: LILA-001 | C165: P150 | D165: 152 | L165: In Stock
A166: LL01-00000000153 | B166: LILA-001 | C166: P150 | D166: 153 | L166: In Stock
A167: LL01-00000000154 | B167: LILA-001 | C167: P150 | D167: 154 | L167: In Stock
A168: LL01-00000000155 | B168: LILA-001 | C168: P150 | D168: 155 | L168: In Stock
A169: LL01-00000000156 | B169: LILA-001 | C169: P150 | D169: 156 | L169: In Stock
A170: LL01-00000000157 | B170: LILA-001 | C170: P150 | D170: 157 | L170: In Stock
... A213: LL01-00000000200 | B213: LILA-001 | C213: P150 | D213: 200 | L213: In Stock
A214: LL01-00000000201 | B214: LILA-001 | C214: P50N | D214: 201 | F214: 2026-03-05 | G214: Jeremiah Pauw | H214: 250-278-6788 | I214: 2021 Hwy 3, Fernie, BC, V0B 1M1 | J214: Canpar | K214: D420352470001907597001 | L214: Delivered | M214: SHP-CA-022 | O214: =F214+730 -> 46816
A215: LL01-00000000202 | B215: LILA-001 | C215: P50N | D215: 202 | F215: 2026-03-03 | G215: Kaiti Klucas | H215: 570-419-8076 | I215: 8634 Union Ridge Dr, Hokah, MN, 55941 | J215: UPS | K215: 1ZV56D26DK00652359 | L215: Delivered | M215: SHP-US-043 | O215: =F215+730 -> 46814
A216: LL01-00000000203 | B216: LILA-001 | C216: P50N | D216: 203 | F216: 2026-03-13 | G216: Audrey Balanay-St John | H216: 904-208-0720 | I216: 140 Lakes Blvd, Kingsland, GA, 31548 | J216: UPS | K216: 1ZV56D26DK23942494 | L216: Delivered | M216: SHP-US-062 | O216: =F216+730 -> 46824
A217: LL01-00000000204 | B217: LILA-001 | C217: P50N | D217: 204 | L217: In Stock
A218: LL01-00000000205 | B218: LILA-001 | C218: P50N | D218: 205 | F218: 2026-03-10 | G218: Tricia Bowling | H218: 251-348-6873 | I218: 4150 Shan Dr E, Mobile, AL, 36693 | J218: UPS | K218: 1ZV56D26DK06672193 | L218: Delivered | M218: SHP-US-047 | N218: HS-0076 | O218: =F218+730 -> 46821
A219: LL01-00000000206 | B219: LILA-001 | C219: P50N | D219: 206 | L219: In Stock
A220: LL01-00000000207 | B220: LILA-001 | C220: P50N | D220: 207 | F220: 2026-03-05 | G220: Esmeralda Burgess | H220: 443-820-5971 | I220: 3264 Wendlyn Way, Edgewater, MD, 21037 | J220: UPS | K220: 1ZV56D26DK22305246 | L220: Delivered | M220: SHP-US-046 | O220: =F220+730 -> 46816
A221: LL01-00000000208 | B221: LILA-001 | C221: P50N | D221: 208 | L221: In Stock
A222: LL01-00000000209 | B222: LILA-001 | C222: P50N | D222: 209 | L222: In Stock
...

Sheet Shipping & Tracking
A1: Shipping & Tracking (Freightcom)
A2: Rate quotes, label gen, real-time tracking via Freightcom API
A3: Shipment ID | B3: SO Number | C3: Ship Date | D3: Carrier | E3: Service Level | F3: Origin | G3: Destination | H3: Weight (kg) | I3: Dimensions (LxWxH cm) | J3: Status | K3: Tracking Number | L3: Freightcom Quote ID | M3: Quoted Rate | N3: Actual Cost | O3: Est Delivery Date | P3: Actual Delivery Date | Q3: Recipient Name | R3: Recipient Phone | S3: Delivery Signature | T3: Notes
A4: SHP-CA-001 | C4: 2026-01-29 | D4: UPS | E4: UPS Standard | F4: VirgoHome HQ, Toronto, ON, Canada | G4: 16 Johnstone Ln, Charters Settlement, NB, E3C 0E3 | J4: Delivered | K4: 1ZV56D26DK27263612 | N4: 108.66 | P4: 2026-02-04 | Q4: Amanda McCordic | R4: 506-478-4711 | T4: Serial: LL01-00000000145 | HS-0045 | Shipping damage: pin broke, tray shattered; replacement top lid sent
A5: SHP-CA-002 | C5: 2026-01-30 | D5: Canpar | E5: Canpar Ground | F5: VirgoHome HQ, Toronto, ON, Canada | G5: 2401 Shanna Rd, Carp, ON, K0A 1L0 | J5: Delivered | K5: D556276790000029076001 | N5: 71.08 | P5: 2026-02-05 | Q5: Jason Kemp | R5: 613-791-7734 | T5: Serial: LL01-00000000045
A6: SHP-CA-003 | C6: 2026-02-12 | D6: Purolator | E6: Purolator Express | F6: VirgoHome HQ, Toronto, ON, Canada | G6: 16 Johnstone Ln, Charters Settlement, NB, E3C 0E3 | J6: Delivered | K6: 520331991965 | N6: 38.74 | P6: 2026-02-16 | Q6: Amanda McCordic | R6: 506-478-4711 | T6: Item: Top Lid | HS-0045 | Shipping damage: pin broke, tray shattered; replacement top lid sent
A7: SHP-CA-004 | C7: 2026-02-17 | D7: Canpar | E7: Canpar Ground | F7: VirgoHome HQ, Toronto, ON, Canada | G7: 115 Hillview Rd, Strathmore, AB, T1P 1W2 | J7: Delivered | K7: D556276790000032996001 | N7: 89.12 | P7: 2026-02-24 | Q7: Vicki Myhre | R7: 403-901-9472 | T7: Serial: LL01-00000000126
A8: SHP-CA-005 | C8: 2026-02-17 | D8: Canpar | E8: Canpar Ground | F8: VirgoHome HQ, Toronto, ON, Canada | G8: 395 Redfern Dr, Vanderhoof, BC, V0J 3A2 | J8: Delivered | K8: D420352470001836731001 | N8: 118.72 | P8: 2026-02-27 | Q8: Joan Teichroeb | R8: 250-961-8667 | T8: Serial: LL01-00000000239 | HS-0044 | Electrical cord casing damaged; front/back microswitches broken; P50N replacement arranged
A9: SHP-CA-006 | E9: Standard | F9: VirgoHome HQ, Toronto, ON, Canada | J9: Pending | Q9: Ellery Bunn
A10: SHP-CA-007 | B10: #1088 | E10: Standard | F10: VirgoHome HQ, Toronto, ON, Canada | J10: Pending | Q10: Antonio Gonsalves
A11: SHP-CA-008 | E11: Standard | F11: VirgoHome HQ, Toronto, ON, Canada | J11: Pending | Q11: Connie Beatty
A12: SHP-CA-009 | E12: Standard | F12: VirgoHome HQ, Toronto, ON, Canada | J12: Pending | Q12: Tien Tran | T12: HS-0067 | Chamber replaced; main body crack, P100 needed
A13: SHP-CA-010 | B13: #1083 | E13: Standard | F13: VirgoHome HQ, Toronto, ON, Canada | J13: Pending | Q13: Matthew Mossey | T13: HS-0048 | Machine crack (P100 replacement needed)
A14: SHP-CA-011 | E14: Standard | F14: VirgoHome HQ, Toronto, ON, Canada | J14: Pending | Q14: Salvatore & Julia DeCillis
A15: SHP-CA-012 | B15: #1079 | E15: Standard | F15: VirgoHome HQ, Toronto, ON, Canada | J15: Pending | Q15: Michael Madigan | T15: HS-0049 | Cracks on machine (P100 needed)
A16: SHP-CA-013 | E16: Standard | F16: VirgoHome HQ, Toronto, ON, Canada | J16: Pending | Q16: Chad Lockhart
A17: SHP-CA-014 | E17: Standard | F17: VirgoHome HQ, Toronto, ON, Canada | J17: Pending | Q17: Brian Fryer
A18: SHP-CA-015 | E18: Standard | F18: VirgoHome HQ, Toronto, ON, Canada | J18: Pending | Q18: Sharon Corcoran
A19: SHP-CA-016 | E19: Standard | F19: VirgoHome HQ, Toronto, ON, Canada | J19: Pending | Q19: Chris & Renata Grant | T19: HS-0043 | Major cracks on base; P100 replacement when available
A20: SHP-CA-017 | E20: Standard | F20: VirgoHome HQ, Toronto, ON, Canada | J20: Pending | Q20: Tamara Martin | T20: HS-0046 | Main body crack, crushing chamber crack, rusted screws (P100)
A21: SHP-CA-018 | E21: Standard | F21: VirgoHome HQ, Toronto, ON, Canada | J21: Pending | Q21: Candace Chan | T21: HS-0042 | Unit has crack; P100 replacement pending
A22: SHP-CA-019 | E22: Standard | F22: VirgoHome HQ, Toronto, ON, Canada | J22: Pending | Q22: Zhenghe Zhang | T22: HS-0060 | Broken chamber; home smells; needs replacement
A23: SHP-CA-020 | E23: Standard | F23: VirgoHome HQ, Toronto, ON, Canada | J23: Pending | Q23: Kevin Cheng | T23: HS-0071 | Algo too wet + main body crack (P100 needed)
A24: SHP-CA-021 | E24: Standard | F24: VirgoHome HQ, Toronto, ON, Canada | J24: Pending | Q24: Kirk Beatty
A25: SHP-CA-022 | B25: #1063 | C25: 2026-03-05 | D25: Canpar | E25: Canpar Ground | F25: VirgoHome HQ, Toronto, ON, Canada | G25: 2021 Hwy 3, Fernie, BC, V0B 1M1 | J25: Delivered | K25: D420352470001907597001 | N25: 125.76 | P25: 2026-03-10 | Q25: Jeremiah Pauw | R25: 250-278-6788 | T25: Serial: LL01-00000000201
A26: SHP-CA-023 | B26: #1067 | C26: 2026-03-05 | D26: Canpar | E26: Canpar Ground | F26: VirgoHome HQ, Toronto, ON, Canada | G26: 5601 56a St, Beaumont, AB, T4X 1A7 | J26: Delivered | K26: D420352470001907601001 | N26: 67.9 | P26: 2026-03-11 | Q26: Scott Gilbert | R26: 780-952-9739 | T26: Serial: LL01-00000000122
A27: SHP-CA-024 | B27: #1072 | C27: 2026-02-24 | D27: Canpar | E27: Canpar Ground | F27: VirgoHome HQ, Toronto, ON, Canada | G27: 4367 Pl. Joseph-Lenoir, Saint-Laurent, QC, H4R 3C3 | J27: Delivered | K27: D556276790000035134001 | N27: 66.05 | P27: 2026-02-26 | Q27: Robert Simoneau | R27: 514-777-8247 | T27: Serial: LL01-00000000144 | HS-0064 | Extremely dry compost; connected to dashboard for monitoring
A28: SHP-CA-025 | C28: 2026-03-18 | D28: Canpar | E28: Canpar Ground | F28: VirgoHome HQ, Toronto, ON, Canada | G28: 395 Redfern Dr, Vanderhoof, BC, V0J 3A2 | J28: Delivered | K28: D556276790000042526001 | N28: 132.95 | P28: 2026-03-30 | Q28: Joan Teichroeb | R28: 250-961-8667 | T28: Serial: LL01-00000000109 | P150, 3rd Replacement | HS-0044 | Electrical cord casing damaged; front/back microswitches broken; P50N replacement arranged
A29: SHP-CA-026 | B29: #1070 | E29: Standard | F29: VirgoHome HQ, Toronto, ON, Canada | G29: 4059 207th Street, Langley, BC, V3A 2E2 | J29: Pending | Q29: Ron Russell | R29: 604-834-4451 | T29: Pending fulfillment
A30: SHP-CA-027 | B30: #1075 | E30: Standard | F30: VirgoHome HQ, Toronto, ON, Canada | G30: 135 Hardy Ave (Box 235), Sointula, BC, V0N3E0 | J30: Pending | Q30: Ann Prendergast | R30: 604-250-7085 | T30: HS-0075 | Pending fulfillment
A31: SHP-CA-028 | B31: #1076 | C31: 2026-03-20 | D31: Canpar | E31: Canpar Ground | F31: VirgoHome HQ, Toronto, ON, Canada | G31: 147 Mud Lake Road, Murillo, ON, P0T 2G0 | J31: Delivered | K31: D420352470001966966001 | N31: 131.17 | P31: 2026-03-30 | Q31: Joy Seargeant | R31: 807-630-7618 | T31: Serial: LL01-00000000142 | HS-shipped | Delivered 03/30
A32: SHP-CA-029 | B32: #1093 | E32: Standard | F32: VirgoHome HQ, Toronto, ON, Canada | G32: 4506 Grizzly Hill Rd., Spallumcheen, BC V4Y 0M1 | J32: Pending | Q32: Brent Neave | R32: 604-329-2421 | T32: Gate code: 7676# | HS-0049 | P100 replacement list
A33: SHP-CA-030 | B33: #1094 | E33: Standard | F33: VirgoHome HQ, Toronto, ON, Canada | G33: MAYBE IN PERSON | J33: Pending | Q33: Ashley Wright | T33: Pending - possible in-person delivery
A34: SHP-CA-031 | C34: 2026-03-26 | D34: Canpar | E34: Canpar Ground | F34: VirgoHome HQ, Toronto, ON, Canada | G34: 304 8 Ave, Gleichen, AB, T0J 1N0 | J34: In Transit | K34: D420352470001987399001 | N34: 40.67 | Q34: Jenifer Henry | R34: 403-804-1573 | T34: Item: Top Lid | HS-0057 | Rusted screws; replacement top lid shipped
A35: SHP-CA-032 | C35: 2026-03-25 | D35: Canpar | E35: Canpar Ground | F35: VirgoHome HQ, Toronto, ON, Canada | G35: 499 Main St, Elsipogtog First Nation, NB, E4W 2X5 | J35: Delivered | K35: D420352470001982720001 | N35: 39.32 | P35: 2026-03-30 | Q35: Angeline Purcell | R35: 506-523-7006 | T35: Item: Top Lid | HS-0066 | Front lid opens on its own; top lid shipped
A36: SHP-CA-033 | E36: Standard | F36: VirgoHome HQ, Toronto, ON, Canada | G36: 16 Johnstone Ln, Charters Settlement, NB, E3C 0E3 | J36: Pending | Q36: Amanda McCordic | R36: 506-478-4711 | T36: Item: Top Lid | HS-0045 | Shipping damage: pin broke, tray shattered; replacement top lid sent
A37: SHP-CA-034 | B37: #1096 | E37: Standard | F37: VirgoHome HQ, Toronto, ON, Canada | G37: 304-716 Old Sackville Rd., Lower Sackville, NS, B4C 2K3 | J37: Pending | Q37: Rebecca Campbell | R37: 902-818-8352 | T37: Pending fulfillment
A38: SHP-CA-035 | B38: #1098 | E38: Standard | F38: VirgoHome HQ, Toronto, ON, Canada | G38: 1469 Telephone Rd, Colborne, ON, K0K 1S0 | J38: Pending | Q38: Lisa Clarke | R38: 289-404-2364 | T38: Pending fulfillment
A39: SHP-CA-036 | B39: #1103 | E39: Standard | F39: VirgoHome HQ, Toronto, ON, Canada | G39: 4 Birchlawn Avenue, Scarborough, ON, M1N 1H9 | J39: Pending | Q39: Angela Findlay | R39: 647-775-9377
A40: SHP-CA-037 | E40: Standard | F40: VirgoHome HQ, Toronto, ON, Canada | J40: Pending | Q40: Karolina Chmiel | T40: HS-0073 | Dry compost left chamber; machine has cracks (P100 needed)
A41: SHP-CA-038 | C41: 2026-04-10 | D41: Canpar | E41: Canpar Ground | F41: VirgoHome HQ, Toronto, ON, Canada | G41: 12 Pulla Street, Trenton, ON, K8V 5P7 | J41: In Transit | K41: D420352470002041843001 | N41: 52.07 | Q41: Mary Oskamp | R41: 905-536-6985 | T41: Serial: LL01-00000000005
A42: SHP-US-039 | C42: 2026-02-24 | D42: UPS | E42: UPS Standard International | F42: VirgoHome HQ, Toronto, ON, Canada | G42: 1193 N 1950 E, Layton, UT, 84040 | J42: Delivered | K42: 1ZV56D26DK07619589 | N42: 160.8 | P42: 2026-03-03 | Q42: Teresa Just | R42: 801-425-8250 | T42: Serial: LL01-00000000244
A43: SHP-US-040 | C43: 2026-02-24 | D43: UPS | E43: UPS Standard International | F43: VirgoHome HQ, Toronto, ON, Canada | G43: 1207 Spruce Dr, Greenwood, MO, 64034 | J43: Delivered | K43: 1ZV56D26DK34362984 | N43: 140.75 | P43: 2026-03-03 | Q43: Rodney Richards | R43: 816-456-8317 | T43: Serial: LL01-00000000228
A44: SHP-US-041 | C44: 2026-02-24 | D44: UPS | E44: UPS Standard International | F44: VirgoHome HQ, Toronto, ON, Canada | G44: 731 E Twin Palms Dr, Palm Springs, CA, 92264 | J44: Delivered | K44: 1ZV56D26DK36986995 | N44: 166 | P44: 2026-03-03 | Q44: Jeffrey Van Dyke | R44: 971-344-2438 | T44: Serial: LL01-00000000233 | HS-0072 | Broken chamber (P100 fulfillment list)
A45: SHP-US-042 | C45: 2026-02-24 | D45: UPS | E45: UPS Standard International | F45: VirgoHome HQ, Toronto, ON, Canada | G45: 174 Boyette Rd, Lakeland, GA, 31635 | J45: Delivered | K45: 1ZV56D26DK12089222 | N45: 144.45 | P45: 2026-03-03 | Q45: Amila Smith | R45: 229-412-8866 | T45: Serial: LL01-00000000236
A46: SHP-US-043 | C46: 2026-03-03 | D46: UPS | E46: UPS Standard International | F46: VirgoHome HQ, Toronto, ON, Canada | G46: 8634 Union Ridge Dr, Hokah, MN, 55941 | J46: Delivered | K46: 1ZV56D26DK00652359 | N46: 144.74 | P46: 2026-03-06 | Q46: Kaiti Klucas | R46: 570-419-8076 | T46: Serial: LL01-00000000202
A47: SHP-US-044 | C47: 2026-03-05 | D47: UPS | E47: UPS Standard International | F47: VirgoHome HQ, Toronto, ON, Canada | G47: 2965 Cr-1506J, Owensboro, KY, 42303 | J47: In Transit | K47: 1ZV56D26DK06425441 | N47: 137.81 | Q47: Kristi Blue | R47: 270-316-0404 | T47: Serial: LL01-00000000227
A48: SHP-US-045 | C48: 2026-03-05 | D48: UPS | E48: UPS Standard International | F48: VirgoHome HQ, Toronto, ON, Canada | G48: 84-781 Alahele St, Waianae, HI, 96792 | J48: Delivered | K48: 1ZV56D26DG25936156 | N48: 210.51 | P48: 2026-03-06 | Q48: Keith Taitano | R48: 808-699-0587 | T48: Serial: LL01-00000000211
A49: SHP-US-046 | C49: 2026-03-05 | D49: UPS | E49: UPS Standard International | F49: VirgoHome HQ, Toronto, ON, Canada | G49: 3264 Wendlyn Way, Edgewater, MD, 21037 | J49: Delivered | K49: 1ZV56D26DK22305246 | N49: 128.23 | P49: 2026-03-06 | Q49: Esmeralda Burgess | R49: 443-820-5971 | T49: Serial: LL01-00000000207
A50: SHP-US-047 | B50: #1065 | C50: 2026-03-10 | D50: UPS | E50: UPS Standard International | F50: VirgoHome HQ, Toronto, ON, Canada | G50: 4150 Shan Dr E, Mobile, AL, 36693 | J50: Delivered | K50: 1ZV56D26DK06672193 | N50: 141.33 | P50: 2026-03-12 | Q50: Tricia Bowling | R50: 251-348-6873 | T50: Serial: LL01-00000000205 | HS-0076 | Machine flashing, lid alignment issue
A51: SHP-US-048 | B51: #1071 | C51: 2026-03-12 | D51: UPS | E51: UPS Standard International | F51: VirgoHome HQ, Toronto, ON, Canada | G51: 18303 Muirland St, Detroit, MI, 48221 | J51: Delivered | K51: 1ZV56D26DK37674810 | N51: 128.49 | P51: 2026-03-14 | Q51: Anthony Kurt | R51: 313-502-3452 | T51: Serial: LL01-00000000212 | HS-0075 | Top lid cracked, latch broken
A52: SHP-US-049 | C52: 2026-03-11 | D52: UPS | E52: UPS Standard International | F52: VirgoHome HQ, Toronto, ON, Canada | G52: 10202 Ruffian Ln, Berlin, MD, 21811 | J52: Delivered | K52: 1ZV56D26DK38341918 | N52: 138.09 | P52: 2026-03-14 | Q52: Frank Nikolaidis | R52: 330-705-0764 | T52: Serial: LL01-00000000231
A53: SHP-US-050 | B53: #1074 | C53: 2026-03-11 | D53: UPS | E53: UPS Standard International | F53: VirgoHome HQ, Toronto, ON, Canada | G53: 3 Atwood St, Southborough, MA, 01772 | J53: Delivered | K53: 1ZV56D26DK10390006 | N53: 138.09 | P53: 2026-03-14 | Q53: Sandra Colligan | R53: 508-380-3307 | T53: Serial: LL01-00000000223
A54: SHP-US-051 | C54: 2026-03-11 | D54: UPS | E54: UPS Standard International | F54: VirgoHome HQ, Toronto, ON, Canada | G54: 2775 Oak Ridge Dr, Carson City, NV, 89703 | J54: Delivered | K54: 1ZV56D26DK34720248 | N54: 166.68 | P54: 2026-03-14 | Q54: Heather Hall | R54: 775-297-3381 | T54: Serial: LL01-00000000215
A55: SHP-US-052 | C55: 2026-03-11 | D55: UPS | E55: UPS Standard International | F55: VirgoHome HQ, Toronto, ON, Canada | G55: 1451 Guernseytown Rd, Watertown, CT, 06795 | J55: Delivered | K55: 1ZV56D26DK37979134 | N55: 128.49 | P55: 2026-03-14 | Q55: Peter Lupachino | R55: 203-228-3873 | T55: Serial: LL01-00000000230
A56: SHP-US-053 | C56: 2026-03-12 | D56: UPS | E56: UPS Standard International | F56: VirgoHome HQ, Toronto, ON, Canada | G56: 16431 Avenida Ramada, Desert Hot Springs, CA, 92240 | J56: Delivered | K56: 1ZV56D26DK37424349 | N56: 166.68 | P56: 2026-03-14 | Q56: Thomi Clinton | R56: 760-218-4326 | T56: Serial: LL01-00000000219
A57: SHP-US-054 | C57: 2026-03-12 | D57: UPS | E57: UPS Standard International | F57: VirgoHome HQ, Toronto, ON, Canada | G57: 258 Newtown Turnpike, Wilton, CT, 06897 | J57: Delivered | K57: 1ZV56D26DK39171458 | N57: 128.49 | P57: 2026-03-14 | Q57: Jefy Chacko | R57: 763-670-3926 | T57: Serial: LL01-00000000238 | HS-0070 | Expected crusher, machine received without crusher
A58: SHP-US-055 | B58: #1068 | C58: 2026-03-12 | D58: UPS | E58: UPS Standard International | F58: VirgoHome HQ, Toronto, ON, Canada | G58: 6284 Smith Rd, Hamburg, NY, 14075 | J58: Delivered | K58: 1ZV56D26DK37984360 | N58: 123.9 | P58: 2026-03-14 | Q58: Fred Rice | R58: 814-688-7182 | T58: Serial: LL01-00000000210
A59: SHP-US-056 | B59: #1069 | C59: 2026-03-12 | D59: UPS | E59: UPS Standard International | F59: VirgoHome HQ, Toronto, ON, Canada | G59: 4871 Randee Cir, Pensacola, FL, 32526 | J59: Delivered | K59: 1ZV56D26DK01309291 | N59: 141.33 | P59: 2026-03-17 | Q59: Robert Buckley | R59: 850-696-3184 | T59: Serial: LL01-00000000221
A60: SHP-US-057 | B60: #1073 | C60: 2026-03-12 | D60: UPS | E60: UPS Standard International | F60: VirgoHome HQ, Toronto, ON, Canada | G60: 2605 N Jefferson St, Arlington, VA 22207-1415 | J60: Delivered | K60: 1ZV56D26DK36337632 | N60: 128.49 | P60: 2026-03-17 | Q60: Karon Plasha | R60: 703-534-6858 | T60: Serial: LL01-00000000235
A61: SHP-US-058 | B61: #1074 | C61: 2026-03-12 | D61: UPS | E61: UPS Standard International | F61: VirgoHome HQ, Toronto, ON, Canada | G61: 1084 Ironwood Ct, Glenview, IL, 60025 | J61: Delivered | K61: 1ZV56D26DK09789697 | N61: 138.09 | P61: 2026-03-18 | Q61: Sandra Sweet | R61: 847-917-9141 | T61: Serial: LL01-00000000224
A62: SHP-US-059 | B62: #1077 | C62: 2026-03-13 | D62: UPS | E62: UPS Standard International | F62: VirgoHome HQ, Toronto, ON, Canada | G62: 2365 Cunningham Ln, Moorefield, WV, 26836 | J62: Delivered | K62: 1ZV56D26DK18155292 | N62: 132.37 | P62: 2026-03-18 | Q62: Dixie Bean | R62: 304-257-7716 | T62: Serial: LL01-00000000229
A63: SHP-US-060 | B63: #1078 | C63: 2026-03-13 | D63: UPS | E63: UPS Standard International | F63: VirgoHome HQ, Toronto, ON, Canada | G63: 5528 Ridgemoor Dr, Braselton, GA, 30517 | J63: Delivered | K63: 1ZV56D26DK04334507 | N63: 141.51 | P63: 2026-03-18 | Q63: Suzan Jackovatz | R63: 678-997-7421 | T63: Serial: LL01-00000000218
A64: SHP-US-061 | B64: #1079 | C64: 2026-03-13 | D64: UPS | E64: UPS Standard International | F64: VirgoHome HQ, Toronto, ON, Canada | G64: 1261 Soto St, Seaside, CA, 93955 | J64: Delivered | K64: 1ZV56D26DK28560325 | N64: 166.85 | P64: 2026-03-18 | Q64: Michael Romans | R64: 831-760-0031 | T64: Serial: LL01-00000000216
A65: SHP-US-062 | B65: #1080 | C65: 2026-03-13 | D65: UPS | E65: UPS Standard International | F65: VirgoHome HQ, Toronto, ON, Canada | G65: 140 Lakes Blvd, Kingsland, GA, 31548 | J65: Delivered | K65: 1ZV56D26DK23942494 | N65: 141.51 | P65: 2026-03-18 | Q65: Audrey Balanay-St John | R65: 904-208-0720 | T65: Serial: LL01-00000000203
A66: SHP-US-063 | B66: #1084 | C66: 2026-03-13 | D66: UPS | E66: UPS Standard International | F66: VirgoHome HQ, Toronto, ON, Canada | G66: 910 Angel Trace Ct, Inman, SC, 29349 | J66: Delivered | K66: 1ZV56D26DK25313599 | N66: 138.26 | P66: 2026-03-18 | Q66: Justin Plumley | R66: 864-415-1243 | T66: Serial: LL01-00000000243
A67: SHP-US-064 | C67: 2026-03-13 | D67: UPS | E67: UPS Standard International | F67: VirgoHome HQ, Toronto, ON, Canada | G67: 1207 Spruce Dr, Greenwood, MO, 64034 | J67: Delivered | K67: 1ZV56D26DK15048887 | N67: 37.92 | P67: 2026-03-18 | Q67: Rodney Richards | R67: 816-456-8317 | T67: Item: filter cup module
A68: SHP-US-065 | B68: #1085 | C68: 2026-03-13 | D68: UPS | E68: UPS Standard International | F68: VirgoHome HQ, Toronto, ON, Canada | G68: 4120 Hidden Creek Rd, Port Republic, MD, 20676 | J68: Delivered | K68: 1ZV56D26DK26329419 | N68: 128.66 | P68: 2026-03-18 | Q68: Frederick Whittington | R68: 443-618-1651 | T68: Serial: LL01-00000000234
A69: SHP-US-066 | B69: #1062 | C69: 2026-03-18 | D69: UPS | E69: UPS Standard International | F69: VirgoHome HQ, Toronto, ON, Canada | G69: 2809 Deer Blvd, Yankton, SD, 57078 | J69: Delivered | K69: 1ZV56D26DK34315829 | N69: 144.69 | P69: 2026-03-19 | Q69: Douglas Hanson | R69: 605-660-7298 | T69: Serial: LL01-00000000232 | HS-0077 | Back lid won't close, power button flashing blue
A70: SHP-US-067 | B70: #1086 | C70: 2026-03-20 | D70: UPS | E70: UPS Standard International | F70: VirgoHome HQ, Toronto, ON, Canada | G70: 88 Spring Valley Rd, Hardwick Township, NJ, 07825 | J70: Delivered | K70: 1ZV56D26DK21357951 | N70: 135.34 | P70: 2026-03-19 | Q70: Jean Cotis | R70: 973-224-9459 | T70: Serial: LL01-00000000245
A71: SHP-US-068 | B71: #1087 | C71: 2026-04-01 | D71: UPS | E71: UPS Standard International | F71: VirgoHome HQ, Toronto, ON, Canada | G71: 13431 Raven Flight Dr, Cypress, TX, 77429 | J71: Delivered | K71: 1ZV56D26DK14619146 | N71: 164.08 | P71: 2026-04-08 | Q71: Rashida Lee | R71: 713-819-8539 | T71: Serial: LL01-00000000217
A72: SHP-US-069 | B72: #1088 | D72: UPS | E72: UPS Standard International | F72: VirgoHome HQ, Toronto, ON, Canada | G72: 1500 Sussex Turnpike, Randolph, NJ, 07869 | J72: Pending | Q72: Antonio Cernuto | R72: 973-647-2939
A73: SHP-US-070 | B73: #1090 | D73: UPS | E73: UPS Standard International | F73: VirgoHome HQ, Toronto, ON, Canada | G73: 1695 Saddle Creek Farms Rd, Osteen, FL, 32764 | J73: Pending | Q73: Rick Stauffer | R73: 407-417-0530
A74: SHP-US-071 | B74: #1092 | D74: UPS | E74: UPS Standard International | F74: VirgoHome HQ, Toronto, ON, Canada | G74: 4021 Palo Alto Ave, Yucca Valley, CA, 92284 | J74: Pending | Q74: Dale Bober | R74: 760-799-9286
A75: SHP-US-072 | B75: #1095 | D75: UPS | E75: UPS Standard International | F75: VirgoHome HQ, Toronto, ON, Canada | G75: 20757 Atlantic Puffin Dr, Grand Rapids, MN 55744 | J75: Pending | Q75: Jacob Wenger | R75: 218-301-4249
A76: SHP-US-073 | B76: #1097 | E76: Standard | F76: VirgoHome HQ, Toronto, ON, Canada | G76: 918 Maryland Dr, Vista, CA 92083 | J76: Pending | Q76: Cole Perkins | R76: 619-916-7732
A77: SHP-US-074 | B77: #1099 | E77: Standard | F77: VirgoHome HQ, Toronto, ON, Canada | G77: 100 Hoag Drive, Phoenix, NY, 13135-3314 | J77: Pending | Q77: Tara Dupper | R77: 315-956-8380
A78: SHP-US-075 | B78: #1104 | E78: Standard | F78: VirgoHome HQ, Toronto, ON, Canada | G78: 12827 Lake Vista Dr, Gibsonton, FL, 33534 | J78: Pending | Q78: Katrina Dowd | R78: 813-598-6409
A79: SHP-US-076 | B79: #1107 | E79: Standard | F79: VirgoHome HQ, Toronto, ON, Canada | G79: 500 NE Saddle Ridge Rd, Bentonville, AR, 72712 | J79: Pending | Q79: Louis DiPalma | R79: 303-919-9498

Sheet Products
A1: Product Master Catalog
A2: Central product registry — synced to Shopify & HubSpot
A3: SKU | B3: Product Name | C3: Category | D3: Description | E3: Selling Price | F3: Currency | G3: Unit Cost (BOM) | H3: Margin % | I3: Shopify Product ID | J3: HubSpot Product ID | K3: Weight (kg) | L3: Dimensions (LxWxH cm) | M3: Active | N3: Created Date | O3: Last Modified | P3: Reorder Point | Q3: Reorder Qty | R3: Lead Time (days) | S3: Min Order Qty | T3: Primary Supplier
A4: VH-100 | B4: Virgo Smart Hub | C4: Smart Home | D4: Central smart home hub with WiFi, Zigbee, Z-Wave | E4: 490 | F4: CAD | G4: 43.95 | H4: =(E4-G4)/E4 -> 0.91030612 | I4: SH-PROD-001 | J4: HS-PROD-001 | K4: 0.45 | L4: 15x12x5 | M4: Yes | N4: 2025-06-01 | O4: 2026-04-01 | P4: 25 | Q4: 50 | R4: 14 | S4: 10 | T4: ShenZhen Electronics Co
A5: VH-200 | B5: Virgo Motion Sensor | C5: Sensors | D5: PIR motion sensor with temperature/humidity | E5: 65 | F5: CAD | G5: 32 | H5: =(E5-G5)/E5 -> 0.50769231 | I5: SH-PROD-002 | J5: HS-PROD-002 | K5: 0.08 | L5: 8x5x3 | M5: Yes | N5: 2025-06-01 | O5: 2026-03-15 | P5: 50 | Q5: 100 | R5: 10 | S5: 25 | T5: ShenZhen Electronics Co
A6: VH-300 | B6: Virgo Security Cam | C6: Security | D6: 1080p outdoor camera with night vision, 2-way audio | E6: 890 | F6: CAD | G6: 58.7 | H6: =(E6-G6)/E6 -> 0.93404494 | I6: SH-PROD-003 | J6: HS-PROD-003 | K6: 0.35 | L6: 12x10x8 | M6: Yes | N6: 2025-08-01 | O6: 2026-03-20 | P6: 30 | Q6: 30 | R6: 21 | S6: 5 | T6: OptiLens Taiwan
A7: VH-400 | B7: Virgo Door Lock | C7: Access | D7: Smart deadbolt with fingerprint, keypad, app control | E7: 650 | F7: CAD | G7: 95 | H7: =(E7-G7)/E7 -> 0.85384615 | I7: SH-PROD-004 | J7: HS-PROD-004 | K7: 0.95 | L7: 20x8x6 | M7: Yes | N7: 2025-10-01 | O7: 2026-04-05 | P7: 20 | Q7: 25 | R7: 18 | S7: 5 | T7: LockTech Shenzhen
A8: VH-500 | B8: Virgo Thermostat | C8: Climate | D8: Smart thermostat with learning schedule, voice control | E8: 280 | F8: CAD | G8: 68 | H8: =(E8-G8)/E8 -> 0.75714286 | I8: SH-PROD-005 | J8: HS-PROD-005 | K8: 0.18 | L8: 12x12x3 | M8: Yes | N8: 2026-01-15 | O8: 2026-04-10 | P8: 25 | Q8: 50 | R8: 12 | S8: 10 | T8: ShenZhen Electronics Co

Sheet Customers
A1: Customer Database
A2: Synced contacts from Shopify & HubSpot
A3: Customer ID | B3: Company Name | C3: Contact Name | D3: Email | E3: Phone | F3: Billing Address | G3: Shipping Address | H3: Shopify Customer ID | I3: HubSpot Contact ID | J3: Channel | K3: Total Orders | L3: Total Revenue | M3: Last Order Date | N3: Payment Terms | O3: Notes
A4: CUST-001 | C4: Annmarie Kennedy | F4: Seymour CT, United States | G4: Seymour CT, United States | H4: 10390086385985 | J4: Shopify | K4: 1 | L4: 1037.27 | M4: 2026-04-10 | O4: Email marketing: Not subscribed
A5: CUST-002 | C5: Phayvanh Nanthavongdouangsy | F5: Riverside CA, United States | G5: Riverside CA, United States | H5: 10389666300225 | J5: Shopify | K5: 1 | L5: 1016.36 | M5: 2026-04-10 | O5: Email marketing: Subscribed
A6: CUST-003 | C6: Mary Granger | D6: oskampm@mac.com | E6: 905-536-6985 | H6: 10375550468417 | J6: Shopify | K6: 0 | L6: 0 | O6: Email marketing: Subscribed
A7: CUST-004 | C7: Jill jeannine | H7: 9727853789505 | J7: Shopify | K7: 0 | L7: 0 | O7: Email marketing: Subscribed
A8: CUST-005 | C8: Sarah Harris | F8: CROSBY TX, United States | G8: CROSBY TX, United States | H8: 10388443300161 | J8: Shopify | K8: 1 | L8: 1016.08 | M8: 2026-04-09 | O8: Email marketing: Subscribed
A9: CUST-006 | C9: Kristen Pimentel | F9: Salt Lake City UT, United States | G9: Salt Lake City UT, United States | H9: 10387557679425 | J9: Shopify | K9: 1 | L9: 985.23 | M9: 2026-04-09 | O9: Email marketing: Subscribed
A10: CUST-007 | C10: Grant Bieker | H10: 9823008883009 | J10: Shopify | K10: 0 | L10: 0 | O10: Email marketing: Subscribed
A11: CUST-008 | C11: Angela Findlay | D11: fireandprose17@outlook.com | E11: 647-775-9377 | H11: 10353445568833 | J11: Shopify | K11: 1 | L11: 42.38 | M11: 2026-03-27 | O11: Email marketing: Subscribed
A12: CUST-009 | C12: Louis DiPalma | D12: ljdpdm@me.com | E12: 303-919-9498 | F12: New Rochelle NY, United States | G12: New Rochelle NY, United States | H12: 10390388359489 | J12: Shopify | K12: 1 | L12: 1043.06 | M12: 2026-04-07 | O12: Email marketing: Subscribed
A13: CUST-010 | C13: Pedrum | H13: 9804208922945 | J13: Shopify | K13: 4 | L13: 0 | M13: 2026-04-07 | O13: Email marketing: Subscribed
A14: CUST-011 | C14: Katrina Dowd | D14: katrinadowd83@gmail.com | E14: 813-598-6409 | F14: Omaha NE, United States | G14: Omaha NE, United States | H14: 10367785074049 | J14: Shopify | K14: 1 | L14: 1302.95 | M14: 2026-03-31 | O14: Email marketing: Subscribed
A15: CUST-012 | C15: Matthew Mossey | H15: 10161052082497 | J15: Shopify | K15: 2 | L15: 87.48 | M15: 2026-03-27 | O15: Email marketing: Subscribed
A16: CUST-013 | C16: Elizabeth Antony | H16: 9881558032705 | J16: Shopify | K16: 2 | L16: 262.5 | M16: 2026-03-26 | O16: Email marketing: Subscribed
A17: CUST-014 | C17: Tara Dupper | D17: Tarajdupper@gmail.com | E17: 315-956-8380 | F17: New Port Richey FL, United States | G17: New Port Richey FL, United States | H17: 10378940760385 | J17: Shopify | K17: 1 | L17: 1351.87 | M17: 2026-03-23 | O17: Email marketing: Subscribed
A18: CUST-015 | C18: Lisa Clarke | D18: lisaclarkewell@gmail.com | E18: 289-404-2364 | F18: Enfield NS, Canada | G18: Enfield NS, Canada | H18: 10376521761089 | J18: Shopify | K18: 1 | L18: 127.13 | M18: 2026-03-22 | O18: Email marketing: Subscribed
A19: CUST-016 | C19: Cole Perkins | D19: cperkins39741@gmail.com | E19: 619-916-7732 | F19: Oshawa ON, Canada | G19: Oshawa ON, Canada | H19: 10376264294721 | J19: Shopify | K19: 1 | L19: 1372.36 | M19: 2026-03-22 | O19: Email marketing: Subscribed
A20: CUST-017 | C20: Rebecca Campbell | D20: campbellra652@gmail.com | E20: 902-818-8352 | F20: Belwood ON, Canada | G20: Belwood ON, Canada | H20: 10376245256513 | J20: Shopify | K20: 1 | L20: 19.95 | M20: 2026-03-22 | O20: Email marketing: Subscribed
A21: CUST-018 | C21: Jacob Wenger | D21: wenger.jake@gmail.com | E21: 218-301-4249 | F21: Kinzer PA, United States | G21: Kinzer PA, United States | H21: 10374789808449 | J21: Shopify | K21: 1 | L21: 1372.36 | M21: 2026-03-21 | O21: Email marketing: Subscribed
A22: CUST-019 | C22: Ashley Wright | F22: Pottstown PA, United States | G22: Pottstown PA, United States | H22: 10370220163393 | J22: Shopify | K22: 1 | L22: 1502.89 | M22: 2026-03-19 | O22: Email marketing: Subscribed
A23: CUST-020 | C23: Brent Neave | D23: brent@baker-neave.com | E23: 604-329-2421 | F23: Rocky Mountain House AB, Canada | G23: Rocky Mountain House AB, Canada | H23: 10368789889345 | J23: Shopify | K23: 1 | L23: 1396.49 | M23: 2026-03-18 | O23: Email marketing: Subscribed
A24: CUST-021 | C24: Dale Bober | D24: dalebober@gmail.com | E24: 760-799-9286 | F24: Rosemount MN, United States | G24: Rosemount MN, United States | H24: 10363985166657 | J24: Shopify | K24: 1 | L24: 1346.46 | M24: 2026-03-16 | O24: Email marketing: Subscribed
A25: CUST-022 | C25: Scott Iles | D25: mrscottg@gmail.com | E25: 780-952-9739 | F25: Indianapolis IN, United States | G25: Indianapolis IN, United States | H25: 10363846811969 | J25: Shopify | K25: 1 | L25: 19.78 | M25: 2026-03-16 | O25: Email marketing: Subscribed
A26: CUST-023 | C26: Rick Stauffer | D26: rick@freshveggie.com | E26: 407-417-0530 | F26: Youngsville PA, United States | G26: Youngsville PA, United States | H26: 10360618122561 | J26: Shopify | K26: 1 | L26: 1351.17 | M26: 2026-03-14 | O26: Email marketing: Subscribed
A27: CUST-024 | C27: Pedrum Amin | H27: 10356695408001 | J27: Shopify | K27: 1 | L27: 0 | M27: 2026-03-13 | O27: Email marketing: Subscribed
A28: CUST-025 | C28: Antonio Cernuto | D28: antonio@pur2o.com | E28: 973-647-2939 | F28: San Giuliano Milanese, Italy | G28: San Giuliano Milanese, Italy | H28: 10353090634049 | J28: Shopify | K28: 1 | L28: 1336.32 | M28: 2026-03-11 | O28: Email marketing: Subscribed
A29: CUST-026 | C29: Rashida Lee | D29: happy1today@gmail.com | E29: 713-819-8539 | F29: Aiken SC, United States | G29: Aiken SC, United States | H29: 10339866263873 | J29: Shopify | K29: 1 | L29: 999.61 | M29: 2026-03-06 | O29: Email marketing: Subscribed
A30: CUST-027 | C30: Jean Cotis | D30: designerjeanssalon@yahoo.com | E30: 973-224-9459 | F30: Ajaccio, France | G30: Ajaccio, France | H30: 10322530533697 | J30: Shopify | K30: 1 | L30: 1023.44 | M30: 2026-02-28 | O30: Email marketing: Subscribed
A31: CUST-028 | C31: Frederick Whittington | D31: fawjr61@gmail.com | E31: 443-618-1651 | F31: Richmond TX, United States | G31: Richmond TX, United States | H31: 10321900544321 | J31: Shopify | K31: 1 | L31: 1023.44 | M31: 2026-02-28 | O31: Email marketing: Subscribed
A32: CUST-029 | C32: Justin Plumley | D32: jplumley6@yahoo.com | E32: 864-415-1243 | F32: Gallatin TN, United States | G32: Gallatin TN, United States | H32: 10316831580481 | J32: Shopify | K32: 1 | L32: 1022.27 | M32: 2026-02-27 | O32: Email marketing: Subscribed
A33: CUST-030 | C33: Richard Ahola | F33: Georgetown ON, Canada | G33: Georgetown ON, Canada | H33: 10312826732929 | J33: Shopify | K33: 1 | L33: 1129.99 | M33: 2026-02-26 | O33: Email marketing: Subscribed
A34: CUST-031 | C34: AUDREY BALANAY-ST JOHN | D34: audreystjohn143@gmail.com | E34: 904-208-0720 | F34: Pembroke Pines FL, United States | G34: Pembroke Pines FL, United States | H34: 10309983805761 | J34: Shopify | K34: 1 | L34: 1007.06 | M34: 2026-02-25 | O34: Email marketing: Subscribed
A35: CUST-032 | C35: Michael Romans | D35: xseaman@msn.com | E35: 831-760-0031 | F35: Windham ME, United States | G35: Windham ME, United States | H35: 10309785516609 | J35: Shopify | K35: 1 | L35: 1026.43 | M35: 2026-02-25 | O35: Email marketing: Subscribed
A36: CUST-033 | C36: Suzan Jackovatz | D36: suzan@jackovatz.com | E36: 678-997-7421 | F36: Calgary AB, Canada | G36: Calgary AB, Canada | H36: 10308006429121 | J36: Shopify | K36: 1 | L36: 1008.01 | M36: 2026-02-24 | O36: Email marketing: Subscribed
A37: CUST-034 | C37: Dixie Bean | D37: dixbean@yahoo.com | E37: 304-257-7716 | F37: Murfreesboro TN, United States | G37: Murfreesboro TN, United States | H37: 10304869064065 | J37: Shopify | K37: 1 | L37: 1006.76 | M37: 2026-02-23 | O37: Email marketing: Subscribed
A38: CUST-035 | C38: Joy Seargeant | D38: thejosierave@hotmail.com | E38: 807-630-7618 | F38: Barrie ON, Canada | G38: Barrie ON, Canada | H38: 10304679952769 | J38: Shopify | K38: 1 | L38: 1107.39 | M38: 2026-02-23 | O38: Email marketing: Subscribed
A39: CUST-036 | C39: Ann Prendergast | D39: evirdhgih@gmail.com | E39: 604-250-7085 | F39: Concord NH, United States | G39: Concord NH, United States | H39: 10301919698241 | J39: Shopify | K39: 1 | L39: 1049.99 | M39: 2026-02-22 | O39: Email marketing: Subscribed
A40: CUST-037 | C40: Sandra Sweet | D40: Shschestnut@gmail.com | E40: 847-917-9141 | F40: Tampa FL, United States | G40: Tampa FL, United States | H40: 10301893386625 | J40: Shopify | K40: 1 | L40: 1026.36 | M40: 2026-02-22 | O40: Email marketing: Subscribed
A41: CUST-038 | C41: Karon Plasha | D41: kfplasha@icloud.com | E41: 703-534-6858 | F41: Indianapolis IN, United States | G41: Indianapolis IN, United States | H41: 10301876249985 | J41: Shopify | K41: 1 | L41: 1005.96 | M41: 2026-02-22 | O41: Email marketing: Subscribed
A42: CUST-039 | C42: Robert Simoneau | D42: robert@akamna.com | E42: 514-777-8247 | F42: Vernon BC, Canada | G42: Vernon BC, Canada | H42: 10293649866113 | J42: Shopify | K42: 1 | L42: 1028.99 | M42: 2026-02-19 | O42: Email marketing: Subscribed
A43: CUST-040 | C43: Anthony kurt | D43: tnykurt313@yahoo.com | E43: 313-502-3452 | F43: Mississauga ON, Canada | G43: Mississauga ON, Canada | H43: 10289616985473 | J43: Shopify | K43: 1 | L43: 1006.97 | M43: 2026-02-18 | O43: Email marketing: Subscribed
A44: CUST-041 | C44: ron russell | D44: ron@newcmi.ca | E44: 604-834-4451 | F44: Sooke BC, Canada | G44: Sooke BC, Canada | H44: 10289473249665 | J44: Shopify | K44: 1 | L44: 1049.99 | M44: 2026-02-18 | O44: Email marketing: Subscribed
A45: CUST-042 | C45: Robert Buckley | D45: robert.daniel.buckley@gmail.com | E45: 850-696-3184 | F45: Burnham PA, United States | G45: Burnham PA, United States | H45: 10283994382785 | J45: Shopify | K45: 1 | L45: 1001.65 | M45: 2026-02-16 | O45: Email marketing: Subscribed
... A47: CUST-044 | C47: Scott Gilbert | D47: mrscottg@gmail.com | E47: 780-952-9739 | F47: Bonney Lake WA, United States | G47: Bonney Lake WA, United States | H47: 10274694635905 | J47: Shopify | K47: 1 | L47: 1049.99 | M47: 2026-02-13 | O47: Email marketing: Subscribed
A48: CUST-045 | C48: Melissa Braschuk | H48: 10274502483393 | J48: Shopify | K48: 1 | L48: 43.74 | M48: 2026-02-13 | O48: Email marketing: Subscribed
A49: CUST-046 | C49: Tricia Bowling | D49: Triciab12@gmail.com | E49: 251-348-6873 | F49: Dade City FL, United States | G49: Dade City FL, United States | H49: 10274396299649 | J49: Shopify | K49: 1 | L49: 1001.48 | M49: 2026-02-13 | O49: Email marketing: Subscribed
A50: CUST-047 | C50: Joseph Le | F50: Montreal QC, Canada | G50: Montreal QC, Canada | H50: 10274264571265 | J50: Shopify | K50: 1 | L50: 0 | M50: 2026-02-13 | O50: Email marketing: Subscribed
A51: CUST-048 | C51: Jeremiah Pauw | D51: jeremiah@peacockhospitality.ca | E51: 250-278-6788 | F51: Chilliwack BC, Canada | G51: Chilliwack BC, Canada | H51: 10272394878017 | J51: Shopify | K51: 1 | L51: 1028.99 | M51: 2026-02-12 | O51: Email marketing: Subscribed
A52: CUST-049 | C52: Douglas Hanson | D52: dhanson7298@gmail.com | E52: 605-660-7298 | F52: Crestwood KY, United States | G52: Crestwood KY, United States | H52: 10267867553153 | J52: Shopify | K52: 1 | L52: 996.07 | M52: 2026-02-10 | O52: Email marketing: Subscribed
A53: CUST-050 | C53: Janna Moore | H53: 10267413930049 | J53: Shopify | K53: 0 | L53: 0 | O53: Email marketing: Subscribed

Sheet Settings
A1: Settings & Configuration
A2: Dropdown lists, integration keys, warehouse locations
A4: Warehouse Locations
A5: Location Code | B5: Name | C5: Address | D5: Type
A6: Toronto-01 | B6: Toronto Main Warehouse | C6: 50 Industrial Blvd, Scarborough ON | D6: Primary
A7: Vancouver-01 | B7: Vancouver Distribution | C7: 120 Port Rd, Richmond BC | D7: Secondary
A8: Calgary-01 | B8: Calgary Fulfillment | C8: 80 Logistics Ave, Calgary AB | D8: Fulfillment
A10: Integration Configuration
A11: Platform | B11: API Endpoint | C11: Sync Direction | D11: Sync Frequency | E11: Status
A12: Shopify | B12: https://your-store.myshopify.com/admin/api/2026-01 | C12: Bi-directional | D12: Real-time (webhook) | E12: Active
A13: HubSpot | B13: https://api.hubapi.com/crm/v3 | C13: HubSpot → Sheet (deals as SOs) | D13: Every 15 min | E13: Active
A14: Freightcom | B14: https://api.freightcom.com/v1 | C14: Sheet → Freightcom (quotes, labels, tracking) | D14: On demand | E14: Active
A16: Freightcom Configuration
A17: Setting | B17: Value | C17: Notes
A18: API Key | B18: (enter your Freightcom API key) | C18: From Freightcom dashboard > Settings > API
A19: Default Origin | B19: Toronto-01 | C19: Warehouse code from Locations above
A20: Default Carrier Preference | B20: Purolator, Canada Post, UPS | C20: Comma-separated priority list
A21: Auto-Quote on SO Creation | B21: Yes | C21: Automatically fetch Freightcom rates when new SO created
A22: Tracking Poll Interval | B22: 1 hour | C22: How often to check Freightcom for tracking updates
A23: Label Format | B23: PDF 4x6 | C23: Thermal label format for shipping
A24: Insurance Default | B24: Yes (orders > $500) | C24: Auto-add shipping insurance for high-value orders
A26: Shopify Sync Rules
A27: Rule | B27: Setting | C27: Notes
A28: Import new orders | B28: Automatic | C28: All paid Shopify orders auto-import as SOs
A29: Sync fulfillment back | B29: On SO status = Delivered | C29: Updates Shopify order to Fulfilled + adds tracking
A30: Inventory sync | B30: Bi-directional | C30: Stock changes in either system propagate
A31: New product sync | B31: Shopify → Sheet | C31: New Shopify products auto-create in Products tab
A32: Customer sync | B32: Shopify → Sheet | C32: New customers auto-create in Customers tab
A34: HubSpot Sync Rules
A35: Rule | B35: Setting | C35: Notes
A36: Deal → SO trigger | B36: Deal stage = 'Closed Won' | C36: Only closed-won deals become SOs
A37: Pipeline | B37: Sales Pipeline (default) | C37: Configure which HubSpot pipeline to watch
A38: Contact → Customer | B38: Auto-create | C38: Deal contact auto-creates customer record
A39: SO status → Deal | B39: Bi-directional | C39: SO delivery status updates HubSpot deal properties
A40: Product sync | B40: HubSpot → Sheet | C40: HubSpot line items map to Products tab
A42: QuickBooks Account Mapping
A43: Event in Katana/Sheet | B43: QB Account Type | C43: QB Account Name | D43: Account Code | E43: Notes
A44: SO Confirmed / Shipped | B44: Revenue (AR) | C44: Accounts Receivable | D44: 1200 | E44: SO Total → QB Invoice
A45: PO Goods Received | B45: Expense (AP) | C45: Accounts Payable | D45: 2100 | E45: PO Total → QB Bill
A46: Inventory Adjustment | B46: Asset | C46: Inventory Asset | D46: 1500 | E46: Stock value changes
A47: Manufacturing Cost | B47: COGS | C47: Cost of Goods Sold | D47: 5000 | E47: BOM cost on SO delivery
A48: Product Revenue | B48: Revenue | C48: Product Sales Revenue | D48: 4000 | E48: Per product category
A49: Freight/Shipping | B49: Expense | C49: Shipping Expense | D49: 6200 | E49: Freightcom actual costs
A50: Customer Payment (QB→Sheet) | B50: AR Clearing | C50: Payment Received | D50: 1201 | E50: Updates SO Payment Status
